Workbook

Sheet 2026
A1: =NOW() -> 46234.098 | I1: {=(INDIRECT("I" & ROW() + 1)/INDIRECT("E" & ROW() + 1))} -> 0.71075895 | L1: {=(1 - INDIRECT("I" & ROW()))} -> 0.28924105
E2: =O22 -> 989130 | I2: =O7 -> 703033 | L2: =E2-I2 -> 286097
A3: Last updated | D3: Available to budget | I3: Spent this month | L3: Budgeted this month
C5: January
D6: CATEGORY | E6: WEEK1 (1-6) | G6: WEEK2(7-13) | I6: WEEK3 (14-20) | K6: WEEK4 (21-27) | M6: WEEK5 (23-31) | O6: TOTAL
D7: 🛍️ Expenses | E7: =SUM(E8:F21) -> 95653 | G7: =SUM(G8:H21) -> 344551 | I7: =SUM(I8:J21) -> 32856 | K7: =SUM(K8:L21) -> 218120 | M7: =SUM(M8:M21) -> 11853 | O7: =SUM(E7:N7) -> 703033
D8: Rent & bills | E8: 0 | G8: =282631 - 81315 -> 201316 | I8: 0 | K8: 0 | M8: 0 | O8: =SUM(E8:N8) -> 201316
D9: Groceries | E9: =941+2400+448+636+1986+520+589+1369 -> 8889 | G9: =1992+1390+1993+951+2988+4926+875 -> 15115 | I9: =1190+1845+298+1000+702+329+732+3168+650+329 -> 10243 | K9: =3978+1353+650+329+1201+999+3045+514 -> 12069 | M9: =908+1023+4044+1438+3190 -> 10603 | O9: =SUM(E9:N9) -> 56919
D10: Supplies & home | E10: =658+1250 -> 1908 | G10: =3740+2990+404+2120+239 -> 9493 | I10: 0 | K10: 0 | M10: 0 | O10: =SUM(E10:N10) -> 11401
D11: Dining Out | E11: =4444+3080+604 -> 8128 | G11: =3000+4330 -> 7330 | I11: =3050+4680+4980 -> 12710 | K11: =4973 -> 4973 | M11: 0 | O11: =SUM(E11:N11) -> 33141
D12: Drinking Out | E12: =1250+1250 -> 2500 | G12: =1490+1400+990 -> 3880 | I12: =2280/2+1313+1090 -> 3543 | K12: =2768+2340/2+1300 -> 5238 | M12: =1250 -> 1250 | O12: =SUM(E12:N12) -> 16411
D13: Electronics & digital | E13: 0 | G13: 0 | I13: 0 | K13: 0 | M13: 0 | O13: =SUM(E13:N13) -> 0
D14: Health & medicine | E14: 0 | G14: =6000 -> 6000 | I14: 420 | K14: =6000 -> 6000 | M14: 0 | O14: =SUM(E14:N14) -> 12420
D15: Fashion | E15: 0 | G15: =9890 -> 9890 | I15: 0 | K15: 0 | M15: 0 | O15: =SUM(E15:N15) -> 9890
D16: Vacation | E16: =49764 -> 49764 | G16: =30470 -> 30470 | I16: 0 | K16: 0 | M16: 0 | O16: =SUM(E16:N16) -> 80234
D17: Transport | E17: =8950+3880 -> 12830 | G17: 0 | I17: 0 | K17: 0 | M17: 0 | O17: =SUM(E17:N17) -> 12830
D18: Subscriptions | E18: 2245 | G18: 0 | I18: =4800 -> 4800 | K18: =765+9213+3728 -> 13706 | M18: 0 | O18: =SUM(E18:N18) -> 20751
D19: Gifts & dates | E19: =3750 -> 3750 | G19: 61057 | I19: =2280/2 -> 1140 | K19: =150775+18084 -> 168859 | M19: 0 | O19: =SUM(E19:N19) -> 234806
D20: Entertainment | E20: 0 | G20: 0 | I20: 0 | K20: =3875+600+2800 -> 7275 | M20: 0 | O20: =SUM(E20:N20) -> 7275
D21: Others | E21: =5639 -> 5639 | G21: 0 | I21: 0 | K21: 0 | M21: 0 | O21: =SUM(E21:N21) -> 5639
D22: 💰 Incomes | E22: =SUM(E23:F26) -> 945335 | G22: =SUM(G23:G26) -> 43795 | I22: =SUM(I23:I26) -> 0 | K22: =SUM(K23:K26) -> 0 | M22: =SUM(M23:M26) -> 0 | O22: =SUM(E22:N22) -> 989130
D23: Salary | E23: 945335 | G23: 0 | I23: 0 | K23: 0 | M23: 0 | O23: =SUM(E23:N23) -> 945335
D24: Cafeteria | E24: 0 | G24: 0 | I24: 0 | K24: 0 | M24: 0 | O24: =SUM(E24:N24) -> 0
D25: Gifts | E25: 0 | G25: 0 | I25: 0 | K25: 0 | M25: 0 | O25: =SUM(E25:N25) -> 0
D26: Others | E26: 0 | G26: =43795 -> 43795 | I26: 0 | K26: 0 | M26: 0 | O26: =SUM(E26:N26) -> 43795
A29: =NOW() -> 46234.098 | I29: {=(INDIRECT("I" & ROW() + 1)/INDIRECT("E" & ROW() + 1))} -> 0.59820236 | L29: {=(1 - INDIRECT("I" & ROW()))} -> 0.40179764
E30: =O50 -> 1286130 | I30: =O35 -> 769366 | L30: =E30-I30 -> 516764
A31: Last updated | D31: Available to budget | I31: Spent this month | L31: Budgeted this month
C33: February
D34: CATEGORY | E34: WEEK1 (1-6) | G34: WEEK2(7-13) | I34: WEEK3 (14-20) | K34: WEEK4 (21-27) | M34: WEEK5 (23-31) | O34: TOTAL
D35: 🛍️ Expenses | E35: =SUM(E36:F49) -> 203708 | G35: =SUM(G36:H49) -> 343883 | I35: =SUM(I36:J49) -> 94896 | K35: =SUM(K36:L49) -> 126480 | M35: =SUM(M36:M49) -> 399 | O35: =SUM(E35:N35) -> 769366
D36: Rent & bills | E36: 0 | G36: 209456 | I36: 0 | K36: 0 | M36: 0 | O36: =SUM(E36:N36) -> 209456
D37: Groceries | E37: =2614+469+650+2630+4686+1841+4038+650+329 -> 17907 | G37: =649+1092+4218+3497+3710+385+650 -> 14201 | I37: =2679+2556+4336+385+3705+185+1367 -> 15213 | K37: =2524+1030+2247+3976+2052+3012 -> 14841 | M37: 399 | O37: =SUM(E37:N37) -> 62561
D38: Supplies & home | E38: =1478+1500 -> 2978 | G38: =1098+1098+4290 -> 6486 | I38: =1245+6550+1320 -> 9115 | K38: =1399+1199+1759 -> 4357 | M38: 0 | O38: =SUM(E38:N38) -> 22936
D39: Dining Out | E39: =3532+3500+3500 -> 10532 | G39: =890+3500+891 -> 5281 | I39: =4140+2600 -> 6740 | K39: =3573+3150 -> 6723 | M39: 0 | O39: =SUM(E39:N39) -> 29276
D40: Drinking Out | E40: =2468+1250+1250 -> 4968 | G40: =1313+1300+1530+1250+1490+450 -> 7333 | I40: =1300+1250+1090+2500/2 -> 4890 | K40: =1300+1250+1490+2880/2 -> 5480 | M40: 0 | O40: =SUM(E40:N40) -> 22671
D41: Electronics & digital | E41: 60000 | G41: =7535 -> 7535 | I41: 0 | K41: 0 | M41: 0 | O41: =SUM(E41:N41) -> 67535
D42: Health & medicine | E42: =6000 -> 6000 | G42: 0 | I42: =6000 -> 6000 | K42: 0 | M42: 0 | O42: =SUM(E42:N42) -> 12000
D43: Fashion | E43: 0 | G43: =5995 -> 5995 | I43: 0 | K43: 0 | M43: 0 | O43: =SUM(E43:N43) -> 5995
D44: Vacation | E44: =11320+17760 -> 29080 | G44: 0 | I44: =1500+2454+21550+15345 -> 40849 | K44: 0 | M44: 0 | O44: =SUM(E44:N44) -> 69929
D45: Transport | E45: =8950 -> 8950 | G45: 0 | I45: 0 | K45: 0 | M45: 0 | O45: =SUM(E45:N45) -> 8950
D46: Subscriptions | E46: =2245+1128 -> 3373 | G46: =9106+3649 -> 12755 | I46: =4039+4800 -> 8839 | K46: =760 -> 760 | M46: 0 | O46: =SUM(E46:N46) -> 25727
D47: Gifts & dates | E47: =59920 -> 59920 | G47: =74841 -> 74841 | I47: =2500/2 -> 1250 | K47: =1300+88886+2880/2 -> 91626 | M47: 0 | O47: =SUM(E47:N47) -> 227637
D48: Entertainment | E48: 0 | G48: 0 | I48: 0 | K48: 0 | M48: 0 | O48: =SUM(E48:N48) -> 0
D49: Others | E49: 0 | G49: 0 | I49: =2000 -> 2000 | K49: =2693 -> 2693 | M49: 0 | O49: =SUM(E49:N49) -> 4693
D50: 💰 Incomes | E50: =SUM(E51:F54) -> 947335 | G50: =SUM(G51:G54) -> 338795 | I50: =SUM(I51:I54) -> 0 | K50: =SUM(K51:K54) -> 0 | M50: =SUM(M51:M54) -> 0 | O50: =SUM(E50:N50) -> 1286130
D51: Salary | E51: 947335 | G51: =295000 -> 295000 | I51: 0 | K51: 0 | M51: 0 | O51: =SUM(E51:N51) -> 1242335
D52: Cafeteria | E52: 0 | G52: 0 | I52: 0 | K52: 0 | M52: 0 | O52: =SUM(E52:N52) -> 0
D53: Gifts | E53: 0 | G53: 0 | I53: 0 | K53: 0 | M53: 0 | O53: =SUM(E53:N53) -> 0
D54: Others | E54: 0 | G54: =43795 -> 43795 | I54: 0 | K54: 0 | M54: 0 | O54: =SUM(E54:N54) -> 43795
A57: =NOW() -> 46234.098 | I57: {=(INDIRECT("I" & ROW() + 1)/INDIRECT("E" & ROW() + 1))} -> 0.94887553 | L57: {=(1 - INDIRECT("I" & ROW()))} -> 0.051124474
E58: =O78 -> 991130 | I58: =O63 -> 940459 | L58: =E58-I58 -> 50671
A59: Last updated | D59: Available to budget | I59: Spent this month | L59: Budgeted this month
C61: March
D62: CATEGORY | E62: WEEK1 (1-6) | G62: WEEK2(7-13) | I62: WEEK3 (14-20) | K62: WEEK4 (21-27) | M62: WEEK5 (23-31) | O62: TOTAL
D63: 🛍️ Expenses | E63: =SUM(E64:F77) -> 165520 | G63: =SUM(G64:H77) -> 269465 | I63: =SUM(I64:J77) -> 202782 | K63: =SUM(K64:L77) -> 114664 | M63: =SUM(M64:M77) -> 188028 | O63: =SUM(E63:N63) -> 940459
D64: Rent & bills | E64: 0 | G64: =281000-80127 -> 200873 | I64: 0 | K64: 0 | M64: 0 | O64: =SUM(E64:N64) -> 200873
D65: Groceries | E65: =439+848+1399+1322+2922+1499+2043+3133+837+748+1507 -> 16697 | G65: =359+899+399+999+574+1299+300+2883+1228+2546+850+4495+1418 -> 18249 | I65: =1283+260+558+607+439+349+649+1374 -> 5519 | K65: =5991+1448+843+999+698+2635 -> 12614 | M65: =489+949+2098+894+3753+485+1190 -> 9858 | O65: =SUM(E65:N65) -> 62937
D66: Supplies & home | E66: =885 -> 885 | G66: =1077+897 -> 1974 | I66: =559 -> 559 | K66: 0 | M66: =658 -> 658 | O66: =SUM(E66:N66) -> 4076
D67: Dining Out | E67: =12790/2+2600+3500+2750+2600+3540 -> 21385 | G67: =6440/2+3150 -> 6370 | I67: =7257+3500+3030+2880 -> 16667 | K67: 0 | M67: =3036+2600+4526 -> 10162 | O67: =SUM(E67:N67) -> 54584
D68: Drinking Out | E68: =2600/2+1250+1300+1250+1300 -> 6400 | G68: =1150+2600/2+1880/2+1250+1290+1250 -> 7180 | I68: =1290+1300+1450 -> 4040 | K68: =2340/2 -> 1170 | M68: =3100/2+1300+1250 -> 4100 | O68: =SUM(E68:N68) -> 22890
D69: Electronics & digital | E69: 0 | G69: 0 | I69: 0 | K69: =15000 -> 15000 | M69: 0 | O69: =SUM(E69:N69) -> 15000
D70: Health & medicine | E70: =6000 -> 6000 | G70: =4610 -> 4610 | I70: 0 | K70: 0 | M70: =6000 -> 6000 | O70: =SUM(E70:N70) -> 16610
D71: Fashion | E71: =6995 -> 6995 | G71: =11696 -> 11696 | I71: 0 | K71: =19830+29580+3595 -> 53005 | M71: 23580 | O71: =SUM(E71:N71) -> 95276
D72: Vacation | E72: 0 | G72: 0 | I72: =41415+41411+1862+35511+1970+1576 -> 123745 | K72: =2603+16000+9374 -> 27977 | M72: 0 | O72: =SUM(E72:N72) -> 151722
D73: Transport | E73: =8950 -> 8950 | G73: 0 | I73: =1000 -> 1000 | K73: 0 | M73: 0 | O73: =SUM(E73:N73) -> 9950
D74: Subscriptions | E74: =2245 -> 2245 | G74: =1180+9473 -> 10653 | I74: =4800 -> 4800 | K74: =3728 -> 3728 | M74: 0 | O74: =SUM(E74:N74) -> 21426
D75: Gifts & dates | E75: =2600/2+12790/2+77570+8000 -> 93265 | G75: =2600/2+1880/2+6440/2 -> 5460 | I75: =46452 -> 46452 | K75: =2340/2 -> 1170 | M75: =3100/2+92120 -> 93670 | O75: =SUM(E75:N75) -> 240017
D76: Entertainment | E76: 0 | G76: 0 | I76: 0 | K76: 0 | M76: 0 | O76: =SUM(E76:N76) -> 0
D77: Others | E77: =2698 -> 2698 | G77: =2400 -> 2400 | I77: 0 | K77: 0 | M77: 40000 | O77: =SUM(E77:N77) -> 45098
D78: 💰 Incomes | E78: =SUM(E79:F82) -> 947335 | G78: =SUM(G79:G82) -> 43795 | I78: =SUM(I79:I82) -> 0 | K78: =SUM(K79:K82) -> 0 | M78: =SUM(M79:M82) -> 0 | O78: =SUM(E78:N78) -> 991130
D79: Salary | E79: 947335 | G79: 0 | I79: 0 | K79: 0 | M79: 0 | O79: =SUM(E79:N79) -> 947335
D80: Cafeteria | E80: 0 | G80: 0 | I80: 0 | K80: 0 | M80: 0 | O80: =SUM(E80:N80) -> 0
D81: Gifts | E81: 0 | G81: 0 | I81: 0 | K81: 0 | M81: 0 | O81: =SUM(E81:N81) -> 0
D82: Others | E82: 0 | G82: =43795 -> 43795 | I82: 0 | K82: 0 | M82: 0 | O82: =SUM(E82:N82) -> 43795
A85: =NOW() -> 46234.098 | I85: {=(INDIRECT("I" & ROW() + 1)/INDIRECT("E" & ROW() + 1))} -> 0.71772821 | L85: {=(1 - INDIRECT("I" & ROW()))} -> 0.28227179
E86: =O106 -> 1141903 | I86: =O91 -> 819576 | L86: =E86-I86 -> 322327
A87: Last updated | D87: Available to budget | I87: Spent this month | L87: Budgeted this month
C89: April
D90: CATEGORY | E90: WEEK1 (1-6) | G90: WEEK2(7-13) | I90: WEEK3 (14-20) | K90: WEEK4 (21-27) | M90: WEEK5 (23-31) | O90: TOTAL
D91: 🛍️ Expenses | E91: =SUM(E92:F105) -> 65001 | G91: =SUM(G92:H105) -> 215202 | I91: =SUM(I92:J105) -> 271354 | K91: =SUM(K92:L105) -> 201102 | M91: =SUM(M92:M105) -> 66917 | O91: =SUM(E91:N91) -> 819576
D92: Rent & bills | E92: 0 | G92: 0 | I92: =251938-85969 -> 165969 | K92: 0 | M92: 0 | O92: =SUM(E92:N92) -> 165969
D93: Groceries | E93: =237+1729+2602+3795+3191+1824+700 -> 14078 | G93: =769+1304+355+1675+2265+1605+2510+2291 -> 12774 | I93: =4336+600+355+2676+8998+2307+948 -> 20220 | K93: =4267+674+3712+1757+712+3447+4000+40+499+847 -> 19955 | M93: =1678+2509+456+709 -> 5352 | O93: =SUM(E93:N93) -> 72379
D94: Supplies & home | E94: 3220 | G94: =1865+1219 -> 3084 | I94: 0 | K94: =6730+879+3600+2999 -> 14208 | M94: =2540 -> 2540 | O94: =SUM(E94:N94) -> 23052
D95: Dining Out | E95: =3500+4250 -> 7750 | G95: =2600+3130+2600+4727+7700 -> 20757 | I95: =2600+3500+1050+3800 -> 10950 | K95: =3226+2600+700 -> 6526 | M95: =5070 -> 5070 | O95: =SUM(E95:N95) -> 51053
D96: Drinking Out | E96: =2400/2 -> 1200 | G96: =2490/2+1150+4270+2600/2+2600/2+1250 -> 10515 | I96: =2740/2+2200/2+950+2600/2+700+1250 -> 6670 | K96: =4470+1250+1300+1250 -> 8270 | M96: =1250 -> 1250 | O96: =SUM(E96:N96) -> 27905
D97: Electronics & digital | E97: 0 | G97: 0 | I97: 0 | K97: 0 | M97: =5430 -> 5430 | O97: =SUM(E97:N97) -> 5430
D98: Health & medicine | E98: 0 | G98: =20180 -> 20180 | I98: 0 | K98: =24900+39116 -> 64016 | M98: 0 | O98: =SUM(E98:N98) -> 84196
D99: Fashion | E99: =7785 -> 7785 | G99: 0 | I99: 0 | K99: =11075 -> 11075 | M99: 0 | O99: =SUM(E99:N99) -> 18860
D100: Vacation | E100: 0 | G100: =51236 -> 51236 | I100: 0 | K100: =45945+(9590+1990+3600+500+5050+10377) -> 77052 | M100: 0 | O100: =SUM(E100:N100) -> 128288
D101: Transport | E101: =8950 -> 8950 | G101: 0 | I101: 0 | K101: 0 | M101: 0 | O101: =SUM(E101:N101) -> 8950
D102: Subscriptions | E102: =2245+1138 -> 3383 | G102: =9135+4028 -> 13163 | I102: =4800 -> 4800 | K102: 0 | M102: 0 | O102: =SUM(E102:N102) -> 21346
D103: Gifts & dates | E103: =15335+2400/2 -> 16535 | G103: =2490/2+74538+2600/2+2600/2 -> 78383 | I103: =2740/2+2200/2+57275 -> 59745 | K103: 0 | M103: =43095+(5430-1250) -> 47275 | O103: =SUM(E103:N103) -> 201938
D104: Entertainment | E104: 0 | G104: 0 | I104: 0 | K104: 0 | M104: 0 | O104: =SUM(E104:N104) -> 0
D105: Others | E105: 2100 | G105: =5110 -> 5110 | I105: =1700+2600/2 -> 3000 | K105: 0 | M105: 0 | O105: =SUM(E105:N105) -> 10210
D106: 💰 Incomes | E106: =SUM(E107:F110) -> 1056795 | G106: =SUM(G107:G110) -> 83000 | I106: =SUM(I107:I110) -> 2108 | K106: =SUM(K107:K110) -> 0 | M106: =SUM(M107:M110) -> 0 | O106: =SUM(E106:N106) -> 1141903
D107: Salary | E107: 1013000 | G107: 0 | I107: 0 | K107: 0 | M107: 0 | O107: =SUM(E107:N107) -> 1013000
D108: Cafeteria | E108: 0 | G108: 0 | I108: 0 | K108: 0 | M108: 0 | O108: =SUM(E108:N108) -> 0
D109: Gifts | E109: 0 | G109: 0 | I109: 0 | K109: 0 | M109: 0 | O109: =SUM(E109:N109) -> 0
D110: Others | E110: 43795 | G110: =85000-2000 -> 83000 | I110: =2108 -> 2108 | K110: 0 | M110: 0 | O110: =SUM(E110:N110) -> 128903
...

Sheet 2025
H1: {=(INDIRECT("G" & ROW() + 1)/INDIRECT("C" & ROW() + 1))} -> #DIV/0! | L1: {=(1 - INDIRECT("I" & ROW()))} -> 1
D2: =O22 -> 1015325 | H2: =O7 -> 632019 | K2: =D2-H2 -> 383306
C3: Available to budget | H3: Spent this month | K3: Budgeted this month
C5: January
D6: CATEGORY | E6: WEEK1 | G6: WEEK2 | I6: WEEK3 | K6: WEEK4 | M6: WEEK5 | O6: TOTAL
D7: 🛍️ Expenses | E7: =SUM(E8:F21) -> 54600 | G7: =SUM(G8:H21) -> 272095 | I7: =SUM(I8:J21) -> 158103 | K7: =SUM(K8:L21) -> 105832 | M7: =SUM(M8:M21) -> 41389 | O7: =SUM(E7:N7) -> 632019
D8: Rent & bills | E8: 0 | G8: =(279660-83600) -> 196060 | I8: 3770 | K8: 0 | M8: 0 | O8: =SUM(E8:N8) -> 199830
D9: Groceries | E9: =3227+5607+1898+900+4555 -> 16187 | G9: =499+549+300+4343+600+398+2084+843+1677 -> 11293 | I9: =2647+1693+6771+759+600+1497+2631+4292+4570 -> 25460 | K9: =310+2062+600+3150+389+2640+4523+3726 -> 17400 | M9: =3144+2917+2466+340+1219 -> 10086 | O9: =SUM(E9:N9) -> 80426
D10: Supplies & home | E10: =3547+870+1998 -> 6415 | G10: =810+1600 -> 2410 | I10: 0 | K10: =1219+2573+1599 -> 5391 | M10: 0 | O10: =SUM(E10:N10) -> 14216
D11: Dining Out | E11: =(16150/2) -> 8075 | G11: =(4360/2)+700 -> 2880 | I11: =4180+5601/2+10880 -> 17860.5 | K11: =700 -> 700 | M11: 0 | O11: =SUM(E11:N11) -> 29515.5
D12: Drinking Out | E12: =1109+1070+1150 -> 3329 | G12: =2300/2+900+955 -> 3005 | I12: =800+400+900+790 -> 2890 | K12: =1150+1150+1000+990 -> 4290 | M12: 1270 | O12: =SUM(E12:N12) -> 14784
D13: Electronics & digital | E13: 0 | G13: 0 | I13: 0 | K13: 0 | M13: 0 | O13: =SUM(E13:N13) -> 0
D14: Health & medicine | E14: 0 | G14: 0 | I14: 0 | K14: 33528 | M14: 360 | O14: =SUM(E14:N14) -> 33888
D15: Fashion | E15: 6995 | G15: =2295+8980 -> 11275 | I15: 1295 | K15: 0 | M15: 0 | O15: =SUM(E15:N15) -> 19565
D16: Vacation | E16: 0 | G16: 37314 | I16: 0 | K16: 0 | M16: 26403 | O16: =SUM(E16:N16) -> 63717
D17: Transport | E17: 0 | G17: 0 | I17: 8950 | K17: 0 | M17: 0 | O17: =SUM(E17:N17) -> 8950
D18: Subscriptions | E18: 2245 | G18: 0 | I18: 3596 | K18: 0 | M18: 0 | O18: =SUM(E18:N18) -> 5841
D19: Gifts & dates | E19: =1109+1070+(16150/2) -> 10254 | G19: =(4360/2)+2300/2+900+955 -> 5185 | I19: =15000+40096+33385+800+5601/2+900 -> 92981.5 | K19: =41633+1000+990 -> 43623 | M19: 1270 | O19: =SUM(E19:N19) -> 153313.5
D20: Entertainment | E20: 0 | G20: 0 | I20: 0 | K20: 0 | M20: 0 | O20: =SUM(E20:N20) -> 0
D21: Others | E21: 1100 | G21: =1573+1100 -> 2673 | I21: =1100+200 -> 1300 | K21: 900 | M21: 2000 | O21: =SUM(E21:N21) -> 7973
D22: 💰 Incomes | E22: =SUM(E23:F26) -> 46990 | G22: =SUM(G23:G26) -> 944335 | I22: =SUM(I23:I26) -> 9000 | K22: =SUM(K23:K26) -> 15000 | M22: =SUM(M23:M26) -> 0 | O22: =SUM(E22:N22) -> 1015325
D23: Salary | E23: 0 | G23: 944335 | J23: 0 | K23: 0 | M23: 0 | O23: =SUM(E23:N23) -> 944335
D24: Cafeteria | E24: 0 | H24: 0 | J24: 0 | L24: 0 | M24: 0 | O24: =SUM(E24:N24) -> 0
D25: Gifts | E25: 0 | G25: 0 | I25: 0 | K25: 0 | M25: 0 | O25: =SUM(E25:N25) -> 0
D26: Others | E26: =20000+26990 -> 46990 | G26: 0 | I26: 9000 | K26: 15000 | M26: 0 | O26: =SUM(E26:N26) -> 70990
H29: {=(INDIRECT("I" & ROW() + 1)/INDIRECT("E" & ROW() + 1))} -> #DIV/0! | L29: {=(1 - INDIRECT("I" & ROW()))} -> 1
D30: =O50 -> 965535 | H30: =O35 -> 520128 | K30: =D30-H30 -> 445407
C31: Available to budget | H31: Spent this month | K31: Budgeted this month
C33: February
D34: CATEGORY | E34: WEEK1 | G34: WEEK2 | I34: WEEK3 | K34: WEEK4 | M34: WEEK5 | O34: TOTAL
D35: 🛍️ Expenses | E35: =SUM(E36:F49) -> 143156 | G35: =SUM(G36:H49) -> 268319 | I35: =SUM(I36:J49) -> 68264 | K35: =SUM(K36:L49) -> 40389 | M35: =SUM(M36:M49) -> 0 | O35: =SUM(E35:N35) -> 520128
D36: Rent & bills | E36: 0 | G36: =294021-87010 -> 207011 | I36: 0 | K36: 0 | M36: 0 | O36: =SUM(E36:N36) -> 207011
D37: Groceries | E37: 8105 | G37: =3846+5879+347+600+684+7078+600 -> 19034 | I37: =2714+1000+4074+2188+3385+617+1299+6986 -> 22263 | K37: =2066+2156+1398+550+2330+5111+477+1199+600+4516 -> 20403 | M37: 0 | O37: =SUM(E37:N37) -> 69805
D38: Supplies & home | E38: 0 | G38: =3822+1283 -> 5105 | I38: 0 | K38: 3790 | M38: 0 | O38: =SUM(E38:N38) -> 8895
D39: Dining Out | E39: 0 | G39: =1990+2000 -> 3990 | I39: =2890+4070 -> 6960 | K39: =3490+2000 -> 5490 | M39: 0 | O39: =SUM(E39:N39) -> 16440
D40: Drinking Out | E40: 0 | G40: =1305+990+900 -> 3195 | I40: =1000+1640+1000+940 -> 4580 | K40: =2666+1000+780+2330+1150+940 -> 8866 | M40: 0 | O40: =SUM(E40:N40) -> 16641
D41: Electronics & digital | E41: 0 | G41: 0 | I41: 0 | K41: 0 | M41: 0 | O41: =SUM(E41:N41) -> 0
D42: Health & medicine | E42: 0 | G42: 0 | I42: 0 | K42: 0 | M42: 0 | O42: =SUM(E42:N42) -> 0
D43: Fashion | E43: 0 | G43: 0 | I43: 0 | K43: 0 | M43: 0 | O43: =SUM(E43:N43) -> 0
D44: Vacation | E44: =2200+9108+25000+16643+13720+18380+5915+1473+8220+11527+822+1233+16104+1314+1147 -> 132806 | G44: 0 | I44: 0 | K44: 0 | M44: 0 | O44: =SUM(E44:N44) -> 132806
D45: Transport | G45: =1149 -> 1149 | I45: =450+8950 -> 9400 | K45: 0 | M45: 0 | O45: =SUM(E45:N45) -> 10549
D46: Subscriptions | E46: 2245 | G46: 2790 | I46: 4916 | K46: 0 | M46: 0 | O46: =SUM(E46:N46) -> 9951
D47: Gifts & dates | E47: 0 | G47: =1305+5680/2+900+20000 -> 25045 | I47: =15765+1000+1640+940 -> 19345 | K47: 940 | M47: 0 | O47: =SUM(E47:N47) -> 45330
D48: Entertainment | E48: 0 | G48: 0 | I48: 0 | K48: 0 | M48: 0 | O48: =SUM(E48:N48) -> 0
D49: Others | E49: 0 | G49: 1000 | I49: 800 | K49: 900 | M49: 0 | O49: =SUM(E49:N49) -> 2700
D50: 💰 Incomes | E50: =SUM(E51:F54) -> 965535 | G50: =SUM(G51:G54) -> 0 | I50: =SUM(I51:I54) -> 0 | K50: =SUM(K51:K54) -> 0 | M50: =SUM(M51:M54) -> 0 | O50: =SUM(E50:N50) -> 965535
D51: Salary | E51: 945535 | G51: 0 | I51: 0 | K51: 0 | M51: 0 | O51: =SUM(E51:N51) -> 945535
D52: Cafeteria | E52: 0 | H52: 0 | J52: 0 | L52: 0 | M52: 0 | O52: =SUM(E52:N52) -> 0
D53: Gifts | E53: 0 | G53: 0 | I53: 0 | K53: 0 | M53: 0 | O53: =SUM(E53:N53) -> 0
D54: Others | E54: 20000 | G54: 0 | I54: 0 | K54: 0 | M54: 0 | O54: =SUM(E54:N54) -> 20000
H57: {=(INDIRECT("I" & ROW() + 1)/INDIRECT("E" & ROW() + 1))} -> #DIV/0! | L57: {=(1 - INDIRECT("I" & ROW()))} -> 1
D58: =O78 -> 971887 | H58: =O63 -> 630319 | K58: =D58-H58 -> 341568
C59: Available to budget | H59: Spent this month | K59: Budgeted this month
C61: March
D62: CATEGORY | E62: WEEK1 | G62: WEEK2 | I62: WEEK3 | K62: WEEK4 | M62: WEEK5 | O62: TOTAL
D63: 🛍️ Expenses | E63: =SUM(E64:F77) -> 115886 | G63: =SUM(G64:H77) -> 295012 | I63: =SUM(I64:J77) -> 36247 | K63: =SUM(K64:L77) -> 112771 | M63: =SUM(M64:M77) -> 70403 | O63: =SUM(E63:N63) -> 630319
D64: Rent & bills | E64: 0 | G64: =278521-79256 -> 199265 | I64: 0 | K64: 0 | M64: 0 | O64: =SUM(E64:N64) -> 199265
D65: Groceries | E65: =618+1137+1566+1782+600+4048+1649+1018+1509+500+469 -> 14896 | G65: =1075+3847+600+749+3704+1400+2834+5198 -> 19407 | I65: =1165+1178+6368+932+7527 -> 17170 | K65: =1812+1048+694+600+3949+2494+2597+2633+2607+600 -> 19034 | M65: =7270+1872+316+666+600+4935 -> 15659 | O65: =SUM(E65:N65) -> 86166
D66: Supplies & home | E66: =1825 -> 1825 | G66: 0 | I66: =1700+1738 -> 3438 | K66: =1018+385 -> 1403 | M66: 1257 | O66: =SUM(E66:N66) -> 7923
D67: Dining Out | E67: =1590+8600/2 -> 5890 | G67: =10293/2+15142/2 -> 12717.5 | I67: =1490+6900/2 -> 4940 | K67: =8530/2+3400 -> 7665 | M67: =10822/2 -> 5411 | O67: =SUM(E67:N67) -> 36623.5
D68: Drinking Out | E68: =1000+2780/2+1150 -> 3540 | G68: =940+1300+1150+3248/2+940 -> 5954 | I68: =1150+1400+1165+1150 -> 4865 | K68: =1300+940 -> 2240 | M68: =940+1540 -> 2480 | O68: =SUM(E68:N68) -> 19079
D69: Electronics & digital | E69: 0 | G69: 0 | I69: 0 | K69: 0 | M69: 0 | O69: =SUM(E69:N69) -> 0
D70: Health & medicine | E70: 0 | G70: 0 | I70: 1219 | K70: 0 | M70: =6000+5500 -> 11500 | O70: =SUM(E70:N70) -> 12719
D71: Fashion | E71: 0 | G71: 0 | I71: 0 | K71: 0 | M71: 0 | O71: =SUM(E71:N71) -> 0
D72: Vacation | E72: 0 | G72: 24293 | I72: 0 | K72: 0 | M72: 25405 | O72: =SUM(E72:N72) -> 49698
D73: Transport | E73: 0 | G73: 0 | I73: 0 | K73: 8950 | M73: 0 | O73: =SUM(E73:N73) -> 8950
D74: Subscriptions | E74: 2245 | G74: =699+2790 -> 3489 | I74: 0 | K74: 3596 | M74: 0 | O74: =SUM(E74:N74) -> 9330
D75: Gifts & dates | E75: =1000+2780/2+80000+8600/2 -> 86690 | G75: =940+10293/2+15142/2+990+3248/2+940 -> 17211.5 | I75: =1165+6900/2 -> 4615 | K75: =8530/2+64618 -> 68883 | M75: =10822/2+940+1540 -> 7891 | O75: =SUM(E75:N75) -> 185290.5
D76: Entertainment | E76: 0 | G76: 11875 | I76: 0 | K76: 0 | M76: 0 | O76: =SUM(E76:N76) -> 11875
D77: Others | E77: 800 | G77: 800 | I77: 0 | K77: 1000 | M77: 800 | O77: =SUM(E77:N77) -> 3400
D78: 💰 Incomes | E78: =SUM(E79:F82) -> 965535 | G78: =SUM(G79:G82) -> 0 | I78: =SUM(I79:I82) -> 0 | K78: =SUM(K79:K82) -> 0 | M78: =SUM(M79:M82) -> 6352 | O78: =SUM(E78:N78) -> 971887
D79: Salary | E79: 945535 | G79: 0 | I79: 0 | K79: 0 | M79: 0 | O79: =SUM(E79:N79) -> 945535
D80: Cafeteria | E80: 0 | H80: 0 | J80: 0 | L80: 0 | M80: 0 | O80: =SUM(E80:N80) -> 0
D81: Gifts | E81: 0 | G81: 0 | I81: 0 | K81: 0 | M81: 0 | O81: =SUM(E81:N81) -> 0
D82: Others | E82: 20000 | G82: 0 | I82: 0 | K82: 0 | M82: 6352 | O82: =SUM(E82:N82) -> 26352
H85: {=(INDIRECT("I" & ROW() + 1)/INDIRECT("E" & ROW() + 1))} -> #DIV/0! | L85: {=(1 - INDIRECT("I" & ROW()))} -> 1
D86: =O106 -> 1008847 | H86: =O91 -> 893690 | K86: =D86-H86 -> 115157
C87: Available to budget | H87: Spent this month | K87: Budgeted this month
C89: April
D90: CATEGORY | E90: WEEK1 | G90: WEEK2 | I90: WEEK3 | K90: WEEK4 | M90: WEEK5 | O90: TOTAL
D91: 🛍️ Expenses | E91: =SUM(E92:F105) -> 69246 | G91: =SUM(G92:H105) -> 251756 | I91: =SUM(I92:J105) -> 237832 | K91: =SUM(K92:L105) -> 160328 | M91: =SUM(M92:M105) -> 174528 | O91: =SUM(E91:N91) -> 893690
D92: Rent & bills | E92: 0 | G92: =290906-85453 -> 205453 | I92: 0 | K92: 0 | M92: 0 | O92: =SUM(E92:N92) -> 205453
D93: Groceries | E93: =3567+158+2846+2854+4082 -> 13507 | G93: =898+499+1947+600+3067 -> 7011 | I93: =4268+1318+2080+1165+489+600+3550+5768 -> 19238 | K93: =5938+2114+600+489+3598+1249 -> 13988 | M93: =337+9019+600+1198 -> 11154 | O93: =SUM(E93:N93) -> 64898
D94: Supplies & home | E94: 0 | G94: =1999+778+2298 -> 5075 | I94: =4195+3148 -> 7343 | K94: =720+3448+2336 -> 6504 | M94: =659+5900 -> 6559 | O94: =SUM(E94:N94) -> 25481
D95: Dining Out | E95: =7125/2+31144/2 -> 19134.5 | G95: =2890+8360/2+559+649+5278 -> 13556 | I95: =3470/2+12881/2 -> 8175.5 | K95: =8910+2380+3706 -> 14996 | M95: 0 | O95: =SUM(E95:N95) -> 55862
D96: Drinking Out | E96: =1300+1150+1440 -> 3890 | G96: =940+1150 -> 2090 | I96: =1150+1150 -> 2300 | K96: =850+1150+2930+2780/2 -> 6320 | M96: =1150+1150+800 -> 3100 | O96: =SUM(E96:N96) -> 17700
D97: Electronics & digital | E97: 0 | G97: 0 | I97: 100000 | K97: 0 | M97: =100000+7580 -> 107580 | O97: =SUM(E97:N97) -> 207580
D98: Health & medicine | E98: 0 | G98: 5500 | I98: 0 | K98: 0 | M98: 0 | O98: =SUM(E98:N98) -> 5500
D99: Fashion | E99: 6595 | G99: 0 | I99: 0 | K99: 0 | M99: 3995 | O99: =SUM(E99:N99) -> 10590
D100: Vacation | E100: 0 | G100: 7392 | I100: 0 | K100: 101620 | M100: 0 | O100: =SUM(E100:N100) -> 109012
D101: Transport | E101: 0 | G101: 0 | I101: 0 | K101: 9400 | M101: 0 | O101: =SUM(E101:N101) -> 9400
D102: Subscriptions | E102: 2245 | G102: 699 | I102: 0 | K102: 0 | M102: 0 | O102: =SUM(E102:N102) -> 2944
D103: Gifts & dates | E103: =7125/2+1300+1440+31144/2 -> 21874.5 | G103: =8360/2 -> 4180 | I103: =1140+3470/2+90660+12881/2 -> 99975.5 | K103: =900+1140+2780/2 -> 3430 | M103: =41000+1140 -> 42140 | O103: =SUM(E103:N103) -> 171600
D104: Entertainment | E104: 0 | G104: 0 | I104: 0 | K104: 0 | M104: 0 | O104: =SUM(E104:N104) -> 0
D105: Others | E105: 2000 | G105: 800 | I105: 800 | K105: =3170+900 -> 4070 | M105: 0 | O105: =SUM(E105:N105) -> 7670
D106: 💰 Incomes | E106: =SUM(E107:F110) -> 945335 | G106: =SUM(G107:G110) -> 0 | I106: =SUM(I107:I110) -> 0 | K106: =SUM(K107:K110) -> 0 | M106: =SUM(M107:M110) -> 63512 | O106: =SUM(E106:N106) -> 1008847
D107: Salary | E107: 0 | G107: 0 | I107: 0 | K107: 0 | M107: 0 | O107: =SUM(E107:N107) -> 0
D108: Cafeteria | E108: 0 | H108: 0 | J108: 0 | L108: 0 | M108: 0 | O108: =SUM(E108:N108) -> 0
D109: Gifts | E109: 0 | G109: 0 | I109: 0 | K109: 0 | M109: 0 | O109: =SUM(E109:N109) -> 0
D110: Others | E110: 945335 | G110: 0 | I110: 0 | K110: 0 | M110: 63512 | O110: =SUM(E110:N110) -> 1008847
...

Sheet 2024
H1: {=(INDIRECT("I" & ROW() + 1)/INDIRECT("E" & ROW() + 1))} -> #DIV/0! | L1: {=(1 - INDIRECT("I" & ROW()))} -> 1
D2: =610709+7500 -> 618209 | H2: =O7 -> 468399 | K2: =D2-H2 -> 149810 | M2: 0
C3: Available to budget | H3: Spent this month | K3: Budgeted this month | M3: Pending transactions
C5: January
D6: CATEGORY | E6: WEEK1 | G6: WEEK2 | I6: WEEK3 | K6: WEEK4 | M6: WEEK5 | O6: TOTAL
D7: 🛍️ Expenses | E7: =SUM(E8:F21) -> 22623 | G7: =SUM(G8:H21) -> 275716 | I7: =SUM(I8:J21) -> 31364 | K7: =SUM(K8:L21) -> 111054 | M7: =SUM(M8:M21) -> 27642 | O7: =SUM(E7:N7) -> 468399
D8: Rent & bills | E8: 0 | G8: 206000 | I8: 0 | K8: 0 | M8: 0 | O8: =SUM(E8:N8) -> 206000
D9: Groceries | E9: =8672+710+400+4753+590 -> 15125 | G9: =6229+369+6840+2550+4483+7023 -> 27494 | I9: =7501+403+4254+1524+9428+927 -> 24037 | K9: =4911+899+6938+995+1869 -> 15612 | M9: =7278+2550+7068 -> 16896 | O9: =SUM(E9:N9) -> 99164
D10: Supplies & home | E10: =1088+429+1923 -> 3440 | G10: =300+250+729+8906 -> 10185 | I10: =1599+1578 -> 3177 | K10: =1499+1199+779+15990+600 -> 20067 | M10: 0 | O10: =SUM(E10:N10) -> 36869
D11: Dining Out | E11: 0 | G11: =4048+770 -> 4818 | I11: 0 | K11: 0 | M11: 0 | O11: =SUM(E11:N11) -> 4818
D12: Drinking Out | E12: 3058 | G12: 280 | I12: =1500+2650 -> 4150 | K12: =640+1130+1190 -> 2960 | M12: =1330 -> 1330 | O12: =SUM(E12:N12) -> 11778
D13: Electronics & digital | E13: 0 | G13: 0 | I13: 0 | K13: =33350+14990 -> 48340 | M13: 0 | O13: =SUM(E13:N13) -> 48340
D14: Health & medicine | E14: 0 | G14: =8399+5500 -> 13899 | I14: 0 | K14: 0 | M14: 0 | O14: =SUM(E14:N14) -> 13899
D15: Fashion | E15: 0 | G15: 0 | I15: 0 | K15: 0 | M15: 0 | O15: =SUM(E15:N15) -> 0
D16: Vacation | E16: 0 | G16: 0 | I16: 0 | K16: 0 | M16: 0 | O16: =SUM(E16:N16) -> 0
D17: Transport | E17: 1000 | G17: =450+9500 -> 9950 | I17: 0 | K17: 0 | M17: 0 | O17: =SUM(E17:N17) -> 10950
D18: Subscriptions | E18: 0 | G18: 3090 | I18: 0 | K18: 1830 | M18: 0 | O18: =SUM(E18:N18) -> 4920
D19: Gifts & dates | E19: 0 | G19: 0 | I19: 0 | K19: =18115+1130 -> 19245 | M19: =9416 -> 9416 | O19: =SUM(E19:N19) -> 28661
D20: Entertainment | E20: 0 | G20: 0 | I20: 0 | K20: =(2000+1000) -> 3000 | M20: 0 | O20: =SUM(E20:N20) -> 3000
D21: Others | E21: 0 | G21: 0 | I21: 0 | K21: 0 | M21: 0 | O21: =SUM(E21:N21) -> 0
D22: 💰 Incomes | E22: =SUM(E23:F26) -> 0 | G22: =SUM(H23:H26) -> 0 | I22: =SUM(I23:I26) -> 0 | K22: =SUM(K23:K26) -> 7500 | M22: =SUM(M23:M26) -> 0 | O22: =SUM(E22:N22) -> 7500
D23: Salary | E23: 0 | G23: 0 | I23: 0 | K23: 0 | M23: 0 | O23: =SUM(E23:N23) -> 0
D24: Cafeteria | E24: 0 | H24: 0 | J24: 0 | L24: 0 | M24: 0 | O24: =SUM(E24:N24) -> 0
D25: Gifts | E25: 0 | G25: 0 | I25: 0 | K25: 0 | M25: 0 | O25: =SUM(E25:N25) -> 0
D26: Others | E26: 0 | G26: 0 | I26: 0 | K26: 7500 | M26: 0 | O26: =SUM(E26:N26) -> 7500
H29: {=(INDIRECT("I" & ROW() + 1)/INDIRECT("E" & ROW() + 1))} -> #DIV/0! | L29: {=(1 - INDIRECT("I" & ROW()))} -> 1
D30: =O50 -> 673953 | H30: =O35 -> 590201 | K30: =D30-H30 -> 83752 | M30: 0
C31: Available to budget | H31: Spent this month | K31: Budgeted this month | M31: Pending transactions
C33: February
D34: CATEGORY | E34: WEEK1 | G34: WEEK2 | I34: WEEK3 | K34: WEEK4 | M34: WEEK5 | O34: TOTAL
D35: 🛍️ Expenses | E35: =SUM(E36:F49) -> 21822 | G35: =SUM(G36:H49) -> 269992 | I35: =SUM(I36:J49) -> 247892 | K35: =SUM(K36:L49) -> 39860 | M35: =SUM(M36:M49) -> 10635 | O35: =SUM(E35:N35) -> 590201
D36: Rent & bills | E36: 0 | G36: 203312 | I36: 0 | K36: 0 | M36: 0 | O36: =SUM(E36:N36) -> 203312
D37: Groceries | E37: =2736+1392+3258+4353 -> 11739 | G37: =1887+2367+4468-195+5523+2805 -> 16855 | I37: =398+2851+9686 -> 12935 | K37: =3959+734+449+1757+8856+578 -> 16333 | M37: 999 | O37: =SUM(E37:N37) -> 58861
D38: Supplies & home | E38: 0 | G38: =3046 -> 3046 | I38: 0 | K38: 0 | M38: 998 | O38: =SUM(E38:N38) -> 4044
D39: Dining Out | E39: 0 | G39: =3080+2350 -> 5430 | I39: 804 | K39: 4928 | M39: 0 | O39: =SUM(E39:N39) -> 11162
D40: Drinking Out | E40: 0 | G40: =550+890+(2280-950) -> 2770 | I40: =1850+250 -> 2100 | K40: =2020+1150 -> 3170 | M40: =1144 -> 1144 | O40: =SUM(E40:N40) -> 9184
D41: Electronics & digital | E41: 0 | G41: 0 | I41: =210000+14673 -> 224673 | K41: 13690 | M41: 0 | O41: =SUM(E41:N41) -> 238363
D42: Health & medicine | E42: 4488 | G42: 5000 | I42: 0 | K42: 0 | M42: 0 | O42: =SUM(E42:N42) -> 9488
D43: Fashion | E43: 0 | G43: 0 | I43: 0 | K43: 0 | M43: 1490 | O43: =SUM(E43:N43) -> 1490
D44: Vacation | E44: 0 | G44: 0 | I44: 0 | K44: 0 | M44: 0 | O44: =SUM(E44:N44) -> 0
D45: Transport | E45: 1000 | G45: =450+9500 -> 9950 | I45: 0 | K45: 0 | M45: 0 | O45: =SUM(E45:N45) -> 10950
D46: Subscriptions | E46: 2245 | G46: 3090 | I46: 2990 | K46: 1599 | M46: =4790 -> 4790 | O46: =SUM(E46:N46) -> 14714
D47: Gifts & dates | E47: 2350 | G47: =2350+950+15400 -> 18700 | I47: =2090+2300 -> 4390 | K47: 0 | M47: =1144 -> 1144 | O47: =SUM(E47:N47) -> 26584
D48: Entertainment | E48: 0 | G48: 0 | I48: 0 | K48: 0 | M48: 0 | O48: =SUM(E48:N48) -> 0
D49: Others | E49: 0 | G49: 1839 | I49: 0 | K49: 140 | M49: 70 | O49: =SUM(E49:N49) -> 2049
D50: 💰 Incomes | E50: =SUM(E51:F54) -> 634763 | G50: =SUM(G51:G54) -> 15000 | I50: =SUM(I51:I54) -> 10500 | K50: =SUM(K51:K54) -> 13690 | M50: =SUM(M51:M54) -> 0 | O50: =SUM(E50:N50) -> 673953
D51: Salary | E51: 610350 | G51: 0 | I51: 0 | K51: 0 | M51: 0 | O51: =SUM(E51:N51) -> 610350
D52: Cafeteria | E52: 24413 | H52: 0 | J52: 0 | L52: 0 | M52: 0 | O52: =SUM(E52:N52) -> 24413
D53: Gifts | E53: 0 | G53: 0 | I53: 0 | K53: 0 | M53: 0 | O53: =SUM(E53:N53) -> 0
D54: Others | E54: 0 | G54: 15000 | I54: 10500 | K54: 13690 | M54: 0 | O54: =SUM(E54:N54) -> 39190
H57: {=(INDIRECT("I" & ROW() + 1)/INDIRECT("E" & ROW() + 1))} -> #DIV/0! | L57: {=(1 - INDIRECT("I" & ROW()))} -> 1
D58: =O78 -> 764093 | H58: =O63 -> 691836 | K58: =D58-H58 -> 72257 | M58: 1
C59: Available to budget | H59: Spent this month | K59: Budgeted this month | M59: Pending transactions
C61: March
D62: CATEGORY | E62: WEEK1 | G62: WEEK2 | I62: WEEK3 | K62: WEEK4 | M62: WEEK5 | O62: TOTAL
D63: 🛍️ Expenses | E63: =SUM(E64:F77) -> 38926 | G63: =SUM(G64:H77) -> 58632 | I63: =SUM(I64:J77) -> 285478 | K63: =SUM(K64:L77) -> 298808 | M63: =SUM(M64:M77) -> 9992 | O63: =SUM(E63:N63) -> 691836
D64: Rent & bills | E64: 0 | G64: 0 | I64: 210155 | K64: 0 | M64: 0 | O64: =SUM(E64:N64) -> 210155
D65: Groceries | E65: =718+3956+2646+489+11774 -> 19583 | G65: =3425+699+3356+699+2246+449+5211 -> 16085 | I65: =6584+690+7931+459+5808 -> 21472 | K65: =5480+6543+699+3074+529 -> 16325 | M65: =(9261-1219-1799)+1851+1098 -> 9192 | O65: =SUM(E65:N65) -> 82657
D66: Supplies & home | E66: =598 -> 598 | G66: =999+2098 -> 3097 | I66: =3296+2685 -> 5981 | K66: 1649 | M66: 0 | O66: =SUM(E66:N66) -> 11325
D67: Dining Out | E67: 2350 | G67: =(5680/2) -> 2840 | I67: 1049 | K67: 2800 | M67: 0 | O67: =SUM(E67:N67) -> 9039
D68: Drinking Out | E68: 0 | G68: 1590 | I68: 0 | K68: 0 | M68: 0 | O68: =SUM(E68:N68) -> 1590
D69: Electronics & digital | E69: 0 | G69: 0 | I69: 0 | K69: 0 | M69: 0 | O69: =SUM(E69:N69) -> 0
D70: Health & medicine | E70: 5000 | G70: 0 | I70: 5000 | K70: 4934 | M70: 0 | O70: =SUM(E70:N70) -> 14934
D71: Fashion | E71: 0 | G71: 0 | I71: 3990 | K71: 0 | M71: 0 | O71: =SUM(E71:N71) -> 3990
D72: Vacation | E72: 0 | G72: 0 | I72: 0 | K72: 0 | M72: 0 | O72: =SUM(E72:N72) -> 0
D73: Transport | E73: 1000 | G73: 8950 | I73: 0 | K73: 0 | M73: 0 | O73: =SUM(E73:N73) -> 9950
D74: Subscriptions | E74: 2245 | G74: 3090 | I74: 0 | K74: 0 | M74: 0 | O74: =SUM(E74:N74) -> 5335
D75: Gifts & dates | E75: 2350 | G75: =(2780- 1590)+(5680/2) + 990+3990 + 13970 -> 22980 | I75: =7800+(55480-27500-10000) -> 25780 | K75: =3100 -> 3100 | M75: 0 | O75: =SUM(E75:N75) -> 54210
D76: Entertainment | E76: =(8700-2900) -> 5800 | G76: 0 | I76: 0 | K76: 0 | M76: 800 | O76: =SUM(E76:N76) -> 6600
D77: Others | E77: 0 | G77: 0 | I77: =6000+6051 -> 12051 | K77: 270000 | M77: 0 | O77: =SUM(E77:N77) -> 282051
D78: 💰 Incomes | E78: =SUM(E79:F82) -> 689093 | G78: =SUM(G79:G82) -> 0 | I78: =SUM(I79:I82) -> 0 | K78: =SUM(K79:K82) -> 75000 | M78: =SUM(M79:M82) -> 0 | O78: =SUM(E78:N78) -> 764093
D79: Salary | E79: 664678 | G79: 0 | I79: 0 | K79: 0 | M79: 0 | O79: =SUM(E79:N79) -> 664678
D80: Cafeteria | E80: 24415 | H80: 0 | J80: 0 | L80: 0 | M80: 0 | O80: =SUM(E80:N80) -> 24415
D81: Gifts | E81: 0 | G81: 0 | I81: 0 | K81: 0 | M81: 0 | O81: =SUM(E81:N81) -> 0
D82: Others | E82: 0 | G82: 0 | I82: 0 | K82: 75000 | M82: 0 | O82: =SUM(E82:N82) -> 75000
H85: {=(INDIRECT("I" & ROW() + 1)/INDIRECT("E" & ROW() + 1))} -> #DIV/0! | L85: {=(1 - INDIRECT("I" & ROW()))} -> 1
D86: =O106 -> 910000 | H86: =O91 -> 476726.2 | K86: =D86-H86 -> 433273.8 | M86: 1
C87: Available to budget | H87: Spent this month | K87: Budgeted this month | M87: Pending transactions
C89: April
D90: CATEGORY | E90: WEEK1 | G90: WEEK2 | I90: WEEK3 | K90: WEEK4 | M90: WEEK5 | O90: TOTAL
D91: 🛍️ Expenses | E91: =SUM(E92:F105) -> 35598 | G91: =SUM(G92:H105) -> 277391 | I91: =SUM(I92:J105) -> 42036 | K91: =SUM(K92:L105) -> 109052.2 | M91: =SUM(M92:M105) -> 12649 | O91: =SUM(E91:N91) -> 476726.2
D92: Rent & bills | E92: 0 | G92: 200249 | I92: 0 | K92: 0 | M92: 0 | O92: =SUM(E92:N92) -> 200249
D93: Groceries | E93: =11912+788+1886+2797 -> 17383 | G93: =2042+2046+427+6423+560+3903+790 -> 16191 | I93: =898+974+7263+9782+1213+4844 -> 24974 | K93: =1648+4868+1645+629+2636 -> 11426 | M93: =5600+2663 -> 8263 | O93: =SUM(E93:N93) -> 78237
D94: Supplies & home | E94: 0 | G94: =1985+1199+1596+2678 -> 7458 | I94: =978+200+1750 -> 2928 | K94: 357 | M94: 0 | O94: =SUM(E94:N94) -> 10743
D95: Dining Out | E95: 2390 | G95: 0 | I95: =1090+2350 -> 3440 | K95: =6011.2+3300 -> 9311.2 | M95: 0 | O95: =SUM(E95:N95) -> 15141.2
D96: Drinking Out | E96: =1250+1400+450 -> 3100 | G96: 0 | I96: 1540 | K96: =1200+2380 -> 3580 | M96: =4386 -> 4386 | O96: =SUM(E96:N96) -> 12606
D97: Electronics & digital | E97: 0 | G97: =1099+10000 -> 11099 | I97: 0 | K97: 0 | M97: 0 | O97: =SUM(E97:N97) -> 11099
D98: Health & medicine | E98: 5000 | G98: =3500+1884 -> 5384 | I98: 0 | K98: 4008 | M98: 0 | O98: =SUM(E98:N98) -> 14392
D99: Fashion | E99: 0 | G99: =2795 -> 2795 | I99: 0 | K99: 0 | M99: 0 | O99: =SUM(E99:N99) -> 2795
D100: Vacation | E100: 0 | G100: 0 | I100: 0 | K100: 0 | M100: 0 | O100: =SUM(E100:N100) -> 0
D101: Transport | E101: 1000 | G101: 8950 | I101: 0 | K101: 31590 | M101: 0 | O101: =SUM(E101:N101) -> 41540
D102: Subscriptions | E102: 2245 | G102: =3126+3090 -> 6216 | I102: 0 | K102: 1790 | M102: 0 | O102: =SUM(E102:N102) -> 10251
D103: Gifts & dates | E103: =2500+1080 -> 3580 | G103: =1750+10197+5800 -> 17747 | I103: =1540+(4900-2350) -> 4090 | K103: =11000+990 -> 11990 | M103: 0 | O103: =SUM(E103:N103) -> 37407
D104: Entertainment | E104: 900 | G104: =950+352 -> 1302 | I104: 750 | K104: 0 | M104: 0 | O104: =SUM(E104:N104) -> 2952
D105: Others | E105: 0 | G105: 0 | I105: =3024+1290 -> 4314 | K105: 35000 | M105: 0 | O105: =SUM(E105:N105) -> 39314
D106: 💰 Incomes | E106: =SUM(E107:F110) -> 0 | G106: =SUM(G107:G110) -> 875000 | I106: =SUM(I107:I110) -> 5000 | K106: =SUM(K107:K110) -> 30000 | M106: =SUM(M107:M110) -> 0 | O106: =SUM(E106:N106) -> 910000
D107: Salary | E107: 0 | G107: 855000 | I107: 0 | K107: 0 | M107: 0 | O107: =SUM(E107:N107) -> 855000
D108: Cafeteria | E108: 0 | H108: 0 | J108: 0 | L108: 0 | M108: 0 | O108: =SUM(E108:N108) -> 0
D109: Gifts | E109: 0 | G109: 0 | I109: 0 | K109: 0 | M109: 0 | O109: =SUM(E109:N109) -> 0
D110: Others | E110: 0 | G110: 20000 | I110: 5000 | K110: 30000 | M110: 0 | O110: =SUM(E110:N110) -> 55000
...

Sheet 2023
A1: eras | I1: {=(INDIRECT("I" & ROW() + 1)/INDIRECT("D" & ROW() + 1))} -> 0.5464238 | M1: {=(1 - INDIRECT("I" & ROW()))} -> 0.4535762
A2: =NOW() -> 46234.098 | D2: =SUM(F22:N22) -> 668097 | I2: =SUM(F7:N7) -> 365064.1 | L2: =D2-I2 -> 303032.9 | N2: 0
A3: Last updated | D3: Available to budget | I3: Spent this month | L3: Budgeted this month | N3: Pending transactions
D5: January
A6: WEEK | B6: LIMITS | E6: CATEGORY | F6: WEEK1 | H6: WEEK2 | J6: WEEK3 | L6: WEEK4 | N6: WEEK5 | P6: TOTAL
A7: #1 | B7: 44932 | E7: 🛍️ Expenses | F7: =SUM(F8:F21) -> 80719 | H7: =SUM(H8:H21) -> 84490 | J7: =SUM(J8:J21) -> 91455 | L7: =SUM(L8:L21) -> 14123 | N7: =SUM(N8:N21) -> 94277.1 | P7: =SUM(F7:O7) -> 365064.1
A8: #2 | B8: 45120 | E8: Rent & bills | F8: 41249 | H8: 0 | J8: 0 | N8: 5680 | P8: =SUM(F8:O8) -> 46929
A9: #3 | B9: 14-20 | E9: Groceries | F9: =(6699-1700+1166) -> 6165 | H9: =2493+550+10977-3700-947+5870 -> 15243 | J9: =12517-5790+700+1428 -> 8855 | L9: =2475+580+1968 -> 5023 | N9: 700 | P9: =SUM(F9:O9) -> 35986
A10: #4 | B10: 21-27 | E10: Supplies & home | F10: 0 | H10: 1090 | J10: 0 | L10: =400+7100-3850 -> 3650 | N10: 0 | P10: =SUM(F10:O10) -> 4740
A11: #5 | B11: 28-31 | E11: Dining Out | F11: 4800 | H11: 0 | J11: =6420+2130+2450 -> 11000 | L11: 0 | N11: 0 | P11: =SUM(F11:O11) -> 15800
E12: Drinking Out | F12: 0 | H12: 0 | J12: 0 | L12: 0 | N12: 0 | P12: =SUM(F12:O12) -> 0
E13: Electronics & digital | F13: =7197+790 -> 7987 | H13: 43480 | J13: 0 | L13: 0 | N13: 0 | P13: =SUM(F13:O13) -> 51467
E14: Health & medicine | F14: 0 | H14: 0 | J14: 70000 | L14: =3850 -> 3850 | N14: 2608 | P14: =SUM(F14:O14) -> 76458
E15: Fashion | F15: 0 | H15: 0 | J15: 0 | L15: 0 | N15: 0 | P15: =SUM(F15:O15) -> 0
E16: Vacation | F16: 0 | H16: 0 | J16: 0 | L16: 0 | N16: =(20+1.44+8.41+4.18+8.9+1.45+1.45+5.7+9.95+6.95+15.5+0.63+30+8.3+5.2+37+4.4+27.35+3.53+5.95+4.4+3+5)*390 -> 85289.1 | P16: =SUM(F16:O16) -> 85289.1
E17: Transport | F17: 16048 | H17: 9500 | J17: 0 | L17: 0 | N17: 0 | P17: =SUM(F17:O17) -> 25548
E18: Subscriptions | F18: 0 | H18: 0 | J18: 1600 | L18: 1600 | N18: 0 | P18: =SUM(F18:O18) -> 3200
E19: Gifts | F19: 4470 | H19: 0 | J19: 0 | L19: 0 | N19: 0 | P19: =SUM(F19:O19) -> 4470
E20: Entertainment | F20: 0 | H20: 1500 | J20: 0 | L20: 0 | N20: 0 | P20: =SUM(F20:O20) -> 1500
E21: Others | F21: 0 | H21: 13677 | J21: 0 | L21: 0 | N21: 0 | P21: =SUM(F21:O21) -> 13677
E22: 💰 Incomes | F22: =SUM(F23:F26) -> 668097 | H22: =SUM(H23:H26) -> 0 | J22: =SUM(K23:K26) -> 0 | L22: =SUM(L23:L26) -> 0 | N22: =SUM(N23:N26) -> 0 | P22: =SUM(F22:O22) -> 668097
E23: Salary | F23: 668097 | H23: 0 | J23: 0 | L23: 0 | N23: 0 | P23: =SUM(F23:O23) -> 668097
E24: Cafeteria | F24: 0 | I24: 0 | K24: 0 | M24: 0 | N24: 0 | P24: =SUM(F24:O24) -> 0
E25: Gifts | F25: 0 | H25: 0 | J25: 0 | L25: 0 | N25: 0 | P25: =SUM(F25:O25) -> 0
E26: Others | F26: 0 | H26: 0 | J26: 0 | L26: 0 | N26: 0 | P26: =SUM(F26:O26) -> 0
I29: {=(INDIRECT("I" & ROW() + 1)/INDIRECT("D" & ROW() + 1))} -> 0.48433081 | M29: {=(1 - INDIRECT("I" & ROW()))} -> 0.51566919
D30: =SUM(F50:N50) -> 679550 | I30: =SUM(F35:N35) -> 329127 | L30: =D30-I30 -> 350423 | N30: 0
D31: Available to budget | I31: Spent this month | L31: Budgeted this month | N31: Pending transactions
D33: February
A34: WEEK | B34: LIMITS | E34: CATEGORY | F34: WEEK1 | H34: WEEK2 | J34: WEEK3 | L34: WEEK4 | N34: WEEK5 | P34: TOTAL
A35: #1 | B35: 44932 | E35: 🛍️ Expenses | F35: =SUM(F36:F49) -> 30431 | H35: =SUM(H36:H49) -> 172647 | J35: =SUM(J36:J49) -> 105400 | L35: =SUM(L36:L49) -> 16314 | N35: =SUM(N36:N49) -> 4335 | P35: =SUM(F35:O35) -> 329127
A36: #2 | B36: 45120 | E36: Rent & bills | F36: 0 | H36: =119957+5680 -> 125637 | J36: 0 | L36: 0 | N36: 0 | P36: =SUM(F36:O36) -> 125637
A37: #3 | B37: 14-20 | E37: Groceries | F37: =4039+5558+620+1884 -> 12101 | H37: =729+2903+1056+1604+620+2048 -> 8960 | J37: =2364+5192+497+620+669+4310 -> 13652 | L37: =2061+570+620+2675+1399+269+600+580 -> 8774 | N37: 1790 | P37: =SUM(F37:O37) -> 45277
A38: #4 | B38: 21-27 | E38: Supplies & home | F38: 0 | H38: =1570+3197+4790 -> 9557 | J38: =1900+6990+938 -> 9828 | L38: 1250 | N38: 0 | P38: =SUM(F38:O38) -> 20635
A39: #5 | B39: 28-31 | E39: Dining Out | F39: =1270+2250 -> 3520 | H39: =1790+4850+2610+2140 -> 11390 | J39: =2190+2400+2190 -> 6780 | L39: =2045+2645 -> 4690 | N39: 2545 | P39: =SUM(F39:O39) -> 28925
E40: Drinking Out | F40: 0 | H40: 2180 | J40: 2500 | L40: 0 | N40: 0 | P40: =SUM(F40:O40) -> 4680
E41: Electronics & digital | F41: 3790 | H41: 0 | J41: 0 | L41: 0 | N41: 0 | P41: =SUM(F41:O41) -> 3790
E42: Health & medicine | F42: 5000 | H42: 0 | J42: 70000 | L42: 0 | N42: 0 | P42: =SUM(F42:O42) -> 75000
E43: Fashion | F43: 0 | H43: 0 | J43: 0 | L43: 0 | N43: 0 | P43: =SUM(F43:O43) -> 0
E44: Vacation | F44: 0 | H44: 0 | J44: 0 | L44: 0 | N44: 0 | P44: =SUM(F44:O44) -> 0
E45: Transport | F45: =4030 -> 4030 | H45: 9500 | J45: 0 | L45: 0 | N45: 0 | P45: =SUM(F45:O45) -> 13530
E46: Subscriptions | F46: 1990 | H46: 1663 | J46: 0 | L46: 1600 | N46: 0 | P46: =SUM(F46:O46) -> 5253
E47: Gifts | F47: 0 | H47: 0 | J47: 0 | L47: 0 | N47: 0 | P47: =SUM(F47:O47) -> 0
E48: Entertainment | F48: 0 | H48: 1760 | J48: 2640 | L48: 0 | N48: 0 | P48: =SUM(F48:O48) -> 4400
E49: Others | F49: 0 | H49: 2000 | J49: 0 | L49: 0 | N49: 0 | P49: =SUM(F49:O49) -> 2000
E50: 💰 Incomes | F50: =SUM(F51:F54) -> 679550 | H50: =SUM(H51:H54) -> 0 | J50: =SUM(K51:K54) -> 0 | L50: =SUM(L51:L54) -> 0 | N50: =SUM(N51:N54) -> 0 | P50: =SUM(F50:O50) -> 679550
E51: Salary | F51: 679550 | H51: 0 | J51: 0 | L51: 0 | N51: 0 | P51: =SUM(F51:O51) -> 679550
E52: Cafeteria | F52: 0 | I52: 0 | K52: 0 | M52: 0 | N52: 0 | P52: =SUM(F52:O52) -> 0
E53: Gifts | F53: 0 | H53: 0 | J53: 0 | L53: 0 | N53: 0 | P53: =SUM(F53:O53) -> 0
E54: Others | F54: 0 | H54: 0 | J54: 0 | L54: 0 | N54: 0 | P54: =SUM(F54:O54) -> 0
I55: {=(INDIRECT("I" & ROW() + 1)/INDIRECT("D" & ROW() + 1))} -> 0.46557972 | M55: {=(1 - INDIRECT("I" & ROW()))} -> 0.53442028
D56: =P76 -> 729570 | I56: =P61 -> 339673 | L56: =D56-I56 -> 389897 | N56: 0
D57: Available to budget | I57: Spent this month | L57: Budgeted this month | N57: Pending transactions
D59: March
A60: WEEK | B60: LIMITS | E60: CATEGORY | F60: WEEK1 | H60: WEEK2 | J60: WEEK3 | L60: WEEK4 | N60: WEEK5 | P60: TOTAL
A61: #1 | B61: 44932 | E61: 🛍️ Expenses | F61: =SUM(F62:F75) -> 51955 | H61: =SUM(H62:H75) -> 162880 | J61: =SUM(J62:J75) -> 18852 | L61: =SUM(L62:L75) -> 59223 | N61: =SUM(N62:N75) -> 46763 | P61: =SUM(F61:O61) -> 339673
A62: #2 | B62: 45120 | E62: Rent & bills | F62: 0 | H62: 108750 | J62: 0 | L62: 0 | N62: 0 | P62: =SUM(F62:O62) -> 108750
A63: #3 | B63: 14-20 | E63: Groceries & food | F63: =717+699+2580+2158+1925+4377+2299 -> 14755 | H63: =1747+700+600+1497+699+1459+4099+2199 -> 13000 | J63: =748+600+781+499+500+1363+1123+649+620+2409 -> 9292 | L63: =7537+1090+703 -> 9330 | N63: =979+6001+2097+500+2801 -> 12378 | P63: =SUM(F63:O63) -> 58755
A64: #4 | B64: 21-27 | E64: Supplies & home | F64: 0 | H64: 2485 | J64: 0 | L64: =600+4490 -> 5090 | N64: =780+895 -> 1675 | P64: =SUM(F64:O64) -> 9250
A65: #5 | B65: 28-31 | E65: Dining Out | F65: =2840+3595+500+2290 -> 9225 | H65: =1270+2085+3490+2390+2215+2290 -> 13740 | J65: =2420 -> 2420 | L65: =2390+2205+2260+2260+3125+2390 -> 14630 | N65: =2285+800+9310+2260+2935+2620 -> 20210 | P65: =SUM(F65:O65) -> 60225
E66: Drinking Out | F66: =1980 -> 1980 | H66: =790+3020 -> 3810 | J66: 1100 | L66: =1680+1590+640 -> 3910 | N66: 0 | P66: =SUM(F66:O66) -> 10800
E67: Electronics & digital | F67: 0 | H67: 0 | J67: 0 | L67: 0 | N67: 0 | P67: =SUM(F67:O67) -> 0
E68: Health & medicine | F68: 10000 | H68: 0 | J68: 3170 | L68: 1678 | N68: 5300 | P68: =SUM(F68:O68) -> 20148
E69: Fashion | F69: 13995 | H69: =15990/2 -> 7995 | J69: 0 | L69: =16590+7995 -> 24585 | N69: 0 | P69: =SUM(F69:O69) -> 46575
E70: Vacation | F70: 0 | H70: 0 | J70: 0 | L70: 0 | N70: 0 | P70: =SUM(F70:O70) -> 0
E71: Transport | F71: 0 | H71: 9500 | J71: 0 | L71: 0 | N71: 0 | P71: =SUM(F71:O71) -> 9500
E72: Subscriptions | F72: 2000 | H72: =1600+2000 -> 3600 | J72: 0 | L72: 0 | N72: 0 | P72: =SUM(F72:O72) -> 5600
E73: Gifts | F73: 0 | H73: 0 | J73: 0 | L73: 0 | N73: 0 | P73: =SUM(F73:O73) -> 0
E74: Entertainment | F74: 0 | H74: 0 | J74: 2870 | L74: 0 | N74: 7200 | P74: =SUM(F74:O74) -> 10070
E75: Others | F75: 0 | H75: 0 | J75: 0 | L75: 0 | N75: 0 | P75: =SUM(F75:O75) -> 0
E76: 💰 Incomes | F76: =SUM(F77:F80) -> 729570 | H76: =SUM(H77:H80) -> 0 | J76: =SUM(K77:K80) -> 0 | L76: =SUM(L77:L80) -> 0 | N76: =SUM(N77:N80) -> 0 | P76: =SUM(F76:O76) -> 729570
E77: Salary | F77: 681943 | H77: 0 | J77: 0 | L77: 0 | N77: 0 | P77: =SUM(F77:O77) -> 681943
E78: Cafeteria | F78: 47627 | I78: 0 | K78: 0 | M78: 0 | N78: 0 | P78: =SUM(F78:O78) -> 47627
E79: Gifts | F79: 0 | H79: 0 | J79: 0 | L79: 0 | N79: 0 | P79: =SUM(F79:O79) -> 0
E80: Others | F80: 0 | H80: 0 | J80: 0 | L80: 0 | N80: 0 | P80: =SUM(F80:O80) -> 0
I81: =(I82/D82) -> 0.64482109 | M81: =(1 - I81) -> 0.35517891
D82: =P102 -> 702812 | I82: =P87 -> 453188 | L82: =D82-I82 -> 249624 | N82: 0
D83: Available to budget | I83: Spent this month | L83: Budgeted this month | N83: Pending transactions
D85: April
A86: WEEK | B86: LIMITS | E86: CATEGORY | F86: WEEK1 | H86: WEEK2 | J86: WEEK3 | L86: WEEK4 | N86: WEEK5 | P86: TOTAL
A87: #1 | B87: 44932 | E87: 🛍️ Expenses | F87: =SUM(F88:F101) -> 33075 | H87: =SUM(H88:H101) -> 163378 | J87: =SUM(J88:J101) -> 71740 | L87: =SUM(L88:L101) -> 180716 | N87: =SUM(N88:N101) -> 4279 | P87: =SUM(F87:O87) -> 453188
A88: #2 | B88: 45120 | E88: Rent & bills | F88: 0 | H88: 113853 | J88: 2060 | L88: 0 | N88: 0 | P88: =SUM(F88:O88) -> 115913
A89: #3 | B89: 14-20 | E89: Groceries & food | F89: =979+1080+7689+627 -> 10375 | H89: =690+850+1951+396+837+600+1491+1594 -> 8409 | J89: =2610+600+959+3379+400 -> 7948 | L89: =3606+600+2671+299 -> 7176 | N89: =600+683+425+1862+709 -> 4279 | P89: =SUM(F89:O89) -> 38187
A90: #4 | B90: 21-27 | E90: Supplies & home | F90: 780 | H90: 0 | J90: =1199+1600 -> 2799 | L90: 0 | N90: 0 | P90: =SUM(F90:O90) -> 3579
A91: #5 | B91: 28-31 | E91: Dining Out | F91: =2380+2785 -> 5165 | H91: =4240+2860+2680+3060 -> 12840 | J91: =900+690+4520+3005+3465+2615 -> 15195 | L91: =3600+3600+2795+3185+3000 -> 16180 | N91: 0 | P91: =SUM(F91:O91) -> 49380
E92: Drinking Out | F92: 0 | H92: =1610+1480 -> 3090 | J92: =1620 -> 1620 | L92: =1700+1400 -> 3100 | N92: 0 | P92: =SUM(F92:O92) -> 7810
E93: Electronics & digital | F93: 0 | H93: 0 | J93: 0 | L93: 0 | N93: 0 | P93: =SUM(F93:O93) -> 0
E94: Health & medicine | F94: 0 | H94: 4599 | J94: 0 | L94: =70000+5000 -> 75000 | N94: 0 | P94: =SUM(F94:O94) -> 79599
E95: Fashion & Care | F95: 0 | H95: =5092 + 5995 -> 11087 | J95: =9590+11995+17034+2499 -> 41118 | L95: =3390+1700+53990 -> 59080 | N95: 0 | P95: =SUM(F95:O95) -> 111285
E96: Vacation | F96: 0 | H96: 0 | J96: 0 | L96: 0 | N96: 0 | P96: =SUM(F96:O96) -> 0
E97: Transport | F97: 0 | H97: 9500 | J97: 1000 | L97: 0 | N97: 0 | P97: =SUM(F97:O97) -> 10500
E98: Subscriptions | F98: 0 | H98: 0 | J98: 0 | L98: 0 | N98: 0 | P98: =SUM(F98:O98) -> 0
E99: Gifts | F99: 0 | H99: 0 | J99: 0 | L99: =3600+6600+(3000+1700) -> 14900 | N99: 0 | P99: =SUM(F99:O99) -> 14900
E100: Entertainment | F100: =7200+2676 -> 9876 | H100: 0 | J100: 0 | L100: 0 | N100: 0 | P100: =SUM(F100:O100) -> 9876
E101: Others | F101: 6879 | H101: 0 | J101: 0 | L101: 5280 | N101: 0 | P101: =SUM(F101:O101) -> 12159
E102: 💰 Incomes | F102: =SUM(F103:F106) -> 702812 | H102: =SUM(H103:H106) -> 0 | J102: =SUM(K103:K106) -> 0 | L102: =SUM(L103:L106) -> 0 | N102: =SUM(N103:N106) -> 0 | P102: =SUM(F102:O102) -> 702812
E103: Salary | F103: 679000 | H103: 0 | J103: 0 | L103: 0 | N103: 0 | P103: =SUM(F103:O103) -> 679000
E104: Cafeteria | F104: 23812 | I104: 0 | K104: 0 | M104: 0 | N104: 0 | P104: =SUM(F104:O104) -> 23812
E105: Gifts | F105: 0 | H105: 0 | J105: 0 | L105: 0 | N105: 0 | P105: =SUM(F105:O105) -> 0
E106: Others | F106: 0 | H106: 0 | J106: 0 | L106: 0 | N106: 0 | P106: =SUM(F106:O106) -> 0
...

Sheet 2022
A1: I spent this much money on this kinda shit
H3: Hónap | I3: JAN | N3: FEB | S3: MÁR | X3: ÁPR
B4: Code | C4: Description | H4: Hét | I4: 1 | J4: 2 | K4: 3 | L4: 4 | M4: 5 | N4: 1 | O4: 2 | P4: 3 | Q4: 4 | R4: 5 | S4: 1 | T4: 2 | U4: 3 | V4: 4 | W4: 5 | X4: 1 | Y4: 2 | Z4: 3 | AA4: 4 | AB4: 5
B5: A | C5: rent+utilities | I5: 55000 | N5: 110000 | S5: =600+600 -> 1200 | X5: 600 | AB5: 86
B6: B | C6: basic food and stuff | I6: =4474+8449 -> 12923 | J6: =1939+280 -> 2219 | K6: =3970+280+1807 -> 6057 | L6: =712+1279+774+2330 -> 5095 | M6: =5488 -> 5488 | N6: =500+1600+778 -> 2878 | O6: =3895+1368+636+547 -> 6446 | P6: =2030+780+1685+1292+399+280 -> 6466 | Q6: =866 -> 866 | R6: =(31+14.38+47.14+8.07+134.16 - 50)*73 -> 13486.75 | S6: =23+10+3.99+2.89+6.2+(120-26+9.88) -> 149.96 | T6: =57+6.5+5+9.5+9.65+6.5 -> 94.15 | U6: =5.35+(112.5-35.57-10)+(2.9+8.93)+(28.77+18.42) -> 131.3 | V6: =3.89+(55.21+38.4-26)+(6.25+51.37) -> 129.12 | W6: =30.54+1+6.99+6.42+10.28+7.7+7.5 -> 70.43 | X6: =16.97+16+31.86+4.99+6+16+11.86+94.74 -> 198.42 | Y6: =4.3+18.16 -> 22.46 | Z6: =3.4+9.38+46.22+32.25 -> 91.25 | AA6: =10.28+3.4 -> 13.68 | AB6: =1+4+26.3 -> 31.3
B7: C | C7: sweets/junk food | M7: =789+159+539+359 -> 1846 | O7: 2500 | P7: 1442 | R7: =5*73 -> 365 | S7: 30 | U7: =6.15+(8+2)+2 -> 18.15 | V7: 24.9 | AA7: 3
B8: D | C8: ordered food/going out | J8: 1700 | K8: =890+890 -> 1780 | L8: 2000 | M8: =530+1975 -> 2505 | N8: =1800+430+460 -> 2690 | O8: =550+1600+590+1800 -> 4540 | P8: =1190+800 -> 1990 | R8: =27*73 -> 1971 | S8: =16.95 -> 16.95 | V8: 10 | AA8: =22 -> 22
B9: E | C9: electronics & tools | R9: =50*73 -> 3650 | U9: =(600+300+20) -> 920 | V9: =1331+1024 -> 2355 | W9: =1770+15+25+12 -> 1822 | Y9: 300
B10: F | C10: clothes | T10: =54.99+34.99 -> 89.98
B11: G | C11: gifts | O11: 20749 | S11: 77 | W11: 40 | X11: =17+23 -> 40 | Z11: 55
B12: H | C12: transport, traveling | I12: 3450 | N12: 3450 | R12: =8000+((2+2+2)*73) -> 8438 | S12: =4+2 -> 6 | T12: =2+2+2 -> 6 | U12: =2+2 -> 4 | V12: =2+2+(2+2) -> 8 | W12: =2 -> 2 | Y12: =11+25+(5+5)+25+(2+2) -> 75 | Z12: =12+3+4 -> 19 | AB12: 50
B13: I | C13: others (vacation, crypto, entertainment, skincare, etc.) | K13: =(300.35+259.81+5+29.45+108.86+47.01+9.9+39.59+64)*73 -> 63069.81 | P13: 495 | Q13: 450 | S13: =55+(32+32+32-32) -> 119 | V13: 81 | AB13: =10+10 -> 20
B14: J | C14: services - dentist, doctor, barber, football,eyecare | I14: 1000 | J14: =1000+3000 -> 4000 | N14: 1000 | O14: 1000 | P14: 1000 | Q14: =3000+1000 -> 4000 | R14: =(320*73) -> 23360 | AA14: 45
B15: K | C15: savings | I15: 222000 | N15: 252101 | R15: 90000 | T15: 3510 | X15: 3510 | AB15: 400
B16: X | C16: out | R16: new frame
B17: Y | C17: in
B18: Z | C18: total
B19: Constants every month:
B20: Netflix | C20: 10
B21: YOXO | C21: 16
I23: MÁJ | N23: JÚN | S23: JÚL | X23: AUG
I24: 1 | J24: 2 | K24: 3 | L24: 4 | M24: 5 | N24: 1 | O24: 2 | P24: 3 | Q24: 4 | R24: 5 | S24: 1 | T24: 2 | U24: 3 | V24: 4 | W24: 5 | X24: 1 | Y24: 2 | Z24: 3 | AA24: 4 | AB24: 5
H25: rent+utilities | I25: 600 | J25: 200 | N25: =600+92.2 -> 692.2 | P25: 81.5 | S25: =28+600+63 -> 691 | T25: 124.8 | U25: =32 -> 32 | X25: 383.84 | Y25: 1200 | AB25: =207250/84 + 260.9 + 485.84 -> 3214.0019
H26: basic food and stuff | I26: =4.9+8.42+57.55+8.98 -> 79.85 | J26: =8.38+16.02+(60.2+11.79)+2.7 -> 99.09 | K26: =40.74+(7.77+30.59)+3.9 -> 83 | L26: =(10+57+8) -> 75 | M26: =(3.15+20.5)+(37.5)+(7.58)+80.84 -> 149.57 | N26: =3.15+(77.94+13.55) -> 94.64 | O26: =17.84+3.15+(2.99+86.52) -> 110.5 | P26: =(3.15+34.4+6.87+(3.15+48.34+28.91)) -> 124.82 | Q26: =(11)+(3.15+(5.95+7.11))+15.87+105+(7+2) -> 157.08 | R26: =(26.93+127.28+12.3+3.15-62) -> 107.66 | S26: =(81.11+10.88-20)+(3.15+16.4) -> 91.54 | T26: =(79.3+33.17-40.72+11.07)+3.15+((47.59+11.76-7)+1) -> 139.32 | U26: =(3.15+11.5)+(3.15+7.6)+(93.04-6.49+12.38-23) -> 101.33 | V26: 40.45 | Z26: =(132.08-50-57) -> 25.08 | AB26: =((2168+22459-8392+2440)+(5406-1600)+(5140+2630-3928))/84 -> 313.36905
H27: sweets/junk food | M27: 7 | P27: =4+22 -> 26 | Q27: =4+(5.09+1.09+1.09) -> 11.27 | U27: =4+6.49 -> 10.49 | V27: =51.39+7.95+27.53+31.34 -> 118.21 | X27: 6
H28: ordered food/eating out | M28: =(22+15.5)+23 -> 60.5 | N28: =13+4.4 -> 17.4 | O28: 33 | Q28: 40 | Z28: =47 -> 47 | AA28: =(7+3.5) -> 10.5 | AB28: =2080/84 -> 24.761905
H29: electronics & supplies | M29: 145 | O29: 83 | Z29: 50 | AB29: =(5275+550-2500)/84 -> 39.583333
H30: clothes | R30: 48.57 | AB30: =3495/84 -> 41.607143
H31: gifts | P31: 65 | Z31: 34
H32: transport | J32: 2 | K32: =2+30 -> 32 | L32: =30+(2+2) -> 34 | M32: 2 | N32: =(25+25)+2+2 -> 54 | O32: =2+2 -> 4 | P32: =(2+5)+2 -> 9 | R32: 21 | S32: 6 | T32: =2+(5+2) -> 9 | U32: =5+2+2 -> 9 | W32: 10 | Y32: =115+31+10 -> 156 | Z32: =(280+5+5) -> 290 | AA32: =(5+5) -> 10 | AB32: =(2530+3000+8800)/84 -> 170.59524
H33: others (entertainment, crypto, etc.) | I33: 17 | N33: 50 | R33: 100 | S33: 30
H34: services(doctor, dentist, barber, massage, courses) | J34: 20 | K34: 3 | L34: 3 | O34: 40 | P34: 70 | T34: =(3+3)+13 -> 19 | U34: 3 | Z34: =(80+40) -> 120 | AB34: =(3000+1000)/84 -> 47.619048
H35: savings | I35: 3510 | J35: 110 | L35: 400 | O35: 3510 | Q35: 142 | T35: 3510 | X35: =(4000+1000) -> 5000 | Y35: =200 -> 200 | Z35: 3565
H36: X | X36: bonusz | Y36: foglalora | AB36: 2ho kaucio+kozk.
H37: Y | Y37: plusz 8k huf+100eur | AB37: bolt+vonat pragaba
H38: Z | AB38: telekom 3k
H42: 84.07 | I42: FORINT
H43: BUDAPEST | I43: SZEP | N43: OKT | S43: NOV | X43: DEC
I44: 1 | J44: 2 | K44: 3 | L44: 4 | M44: 5 | N44: 1 | O44: 2 | P44: 3 | Q44: 4 | R44: 5 | S44: 1 | T44: 2 | U44: 3 | V44: 4 | W44: 5 | X44: 1 | Y44: 2 | Z44: 3 | AA44: 4 | AB44: 5
H45: 1RON TO HUF | I45: 84 | J45: 81 | K45: 83 | L45: 82.2 | M45: 85.26 | N45: 85 | O45: 85.96 | P45: 83 | Q45: 83.36 | R45: 83.75 | S45: 82.72 | T45: 82.81 | U45: 82.27 | V45: 83.24 | W45: 82.97 | X45: 83.15 | Y45: 85.03 | Z45: 82.61 | AA45: 82.2 | AB45: 81.33
H46: rent+utilities (lakber, internet, mobile, rezsi) & home | I46: =(0)/H$42 -> 0 | L46: =1600/L45 -> 19.46472 | O46: =79258/O45 -> 922.0335 | Q46: =3700/Q45 -> 44.385797 | S46: =(82117)/S45 -> 992.71035 | U46: =1600/U45 -> 19.448159 | W46: =(5499)/W45 -> 66.276968 | X46: =(1150+3080+2970+5470-1980-2460-1990)/X45 -> 75.045099 | Y46: =(115453)/Y45 -> 1357.7914 | Z46: =(89322/Z45) -> 1081.2492 | AA46: =(5680/AA45) -> 69.099757
H47: basic food and stuff | I47: =(1106+1157)/H$42 -> 26.918044 | J47: =(15.63+23.56+23.03+31.29)+((2982+8939+8063-748-2229-3020)/J45)+((540+568)/83) -> 279.53841 | K47: =(1136+540-568)/83+(930+800.5+448+623+2558+3864+5289-2075-4015+538)/K45 -> 121.30723 | L47: =((10596+500-3406)+(2263+500+4027-2914-782)+(3960-600+1050))/L45 -> 184.84185 | M47: =(2439-509+500+8436-3920)/M45 -> 81.468449 | N47: =(1756-1076+2781+437+600+1822+650+1220)/N45 -> 96.352941 | O47: =(3000-455+550+4180+1897-1002+3000)/O45 -> 129.94416 | P47: =(1355+857+8447+3868-2767-2190)/P45 -> 115.3012 | Q47: =(1782+550+7900+2949-2003-1200)/Q45 -> 119.6977 | R47: =(312+330+1844+695-345+529+700+1000)/R45 -> 60.477612 | S47: =(4775+1150+793-1887+700+(17875-9081)+1247+528)/S45 -> 194.6325 | T47: =(550+1120+3943+438+700+5445+8875-1958)/T45 -> 230.80546 | U47: =(1102+5209)/U45 -> 76.71083 | V47: =(700+1154+5899+3837+600+12140+4333-4509)/V45 -> 290.17299 | W47: =700/W45 -> 8.4367844 | X47: =(1047+12983-5830)/X45 -> 98.616957 | Y47: =(5002-3000+1288+379+4142+5857-3240-2206+620)/Y45 -> 103.98683 | Z47: =(1817+620)/Z45 -> 29.500061
H48: sweets/junk food | I48: =(0)/H$42 -> 0 | N48: =390/N45 -> 4.5882353 | O48: =455/O45 -> 5.2931596 | R48: =345/R45 -> 4.119403
H49: eating out | I49: =(600+770)/H$42 -> 16.295944 | J49: =((32)+(23.96+21.96+18.77+107.38+19.63+49.35)) -> 273.05 | K49: =(1070+4900)/K45 -> 71.927711 | L49: =(518)/L45 -> 6.3017032 | M49: =(2200)/M45 -> 25.803425 | O49: =(3156+1720+2920)/O45 -> 90.693346 | Q49: =(4800)/Q45 -> 57.581574 | R49: =(990+990)/R45 -> 23.641791 | S49: =(2760+6270+2460)/S45 -> 138.90232 | T49: =(1070+1890)/T45 -> 35.744475 | U49: =(1995)/U45 -> 24.249423 | V49: =(5200)/V45 -> 62.469966 | Z49: =(3100)/Z45 -> 37.525723
H50: electronics & supplies | I50: =(-3000+119000)/H$42 + 374.65 -> 1754.4525 | J50: =(4601/$J45)+12.72 -> 69.522469 | T50: =(24990)/T45 -> 301.77515 | V50: =(1999)/U45 -> 24.298043
H51: clothes | I51: =(3495)/H$42 -> 41.572499 | J51: =82.85 -> 82.85 | K51: =(3499/K45) -> 42.156627 | M51: =19995/M45 -> 234.51795 | N51: =(13985)/N45 -> 164.52941 | T51: =2294/T45 -> 27.701968 | U51: =(21990+20000-7961)/U45 -> 413.62587 | V51: =(1990+3595)/V45 -> 67.095147
H52: gifts | I52: =(0)/H$42 -> 0 | Y52: =(19971-5046)/Y45 -> 175.52628 | Z52: =(20000-8400)/Z45 -> 140.41884
H53: transport & travel | I53: =200 -> 200 | J53: =(14.11 + (9500/83)) -> 128.56783 | O53: =(310+9500)/O45 -> 114.12285 | T53: =9500/T45 -> 114.72044 | Y53: =(9500)/Y45 + (288.31+704.52) -> 1104.5553 | Z53: =(42+16.9+6+12+13.84+4.05+10+10.4+6.5+50)*4.92 -> 844.7148
H54: others (entertainment, crypto, etc.) | I54: =(0)/H$42 -> 0 | J54: =69.92 -> 69.92 | L54: =2800/L45 -> 34.06326 | Q54: =(3880 -980)/Q45 -> 34.788868 | R54: =(9500)/R45 -> 113.43284 | S54: =(2440)/S45 -> 29.497099 | X54: =(5300+13840)/X45 -> 230.18641
H55: services(football, doctor, dentist, barber, massage, courses) | I55: =1000/83 -> 12.048193 | J55: =10 -> 10 | K55: =(3900-1950)/83 -> 23.493976 | L55: =150/L45 + (33677/L45) -> 411.52068 | N55: =(6900+10000+4000+1496)/N45 -> 263.48235 | Q55: =(50000)/Q45 -> 599.80806 | U55: =(70000)/U45 -> 850.85693 | V55: =5000/V45 -> 60.067275 | X55: =(5300)/X45 -> 63.740229
H56: savings | I56: 389 | J56: 3510 | N56: 3571 | S56: =(521942)/S45 + 1671 -> 7980.7437 | X56: =(667210)/X45 -> 8024.1732
H57: X | I57: tg.m->bp balazs | J57: traveling week
H58: Y
H59: Z
B63: 2022
B65: Type | C65: JAN | D65: FEB | E65: MAR | F65: APR | G65: MAJ | H65: JUN | I65: JUL | J65: AUG | K65: SZE | L65: OKT | M65: NOV | N65: DEC | O65: Total Cat.
B66: rent+utilities | C66: =SUM(I5:M5)/72.7 -> 756.5337 | D66: =SUM(N5:R5)/72 -> 1527.7778 | E66: =SUM(S5:W5) -> 1200 | F66: =SUM(X5:AB5) -> 686 | G66: =SUM(I25:M25) -> 800 | H66: =SUM(N25:R25) -> 773.7 | I66: =SUM(S25:W25) -> 847.8 | J66: =SUM(X25:AB25) -> 4797.8419 | K66: =SUM(I46:M46) -> 19.46472 | L66: =SUM(N46:R46) -> 966.4193 | M66: =SUM(S46:W46) -> 1078.4355 | N66: =SUM(X46:AB46) -> 2583.1855 | O66: =SUM(C66:N66) -> 16037.158
B67: basic food and stuff | C67: =SUM(I6:M6)/72.7 -> 437.16644 | D67: =SUM(N6:R6)/72 -> 418.64931 | E67: =SUM(S6:W6) -> 574.96 | F67: =SUM(X6:AB6) -> 357.11 | G67: =SUM(I26:M26) -> 486.51 | H67: =SUM(N26:R26) -> 594.7 | I67: =SUM(S26:W26) -> 372.64 | J67: =SUM(X26:AB26) -> 338.44905 | K67: =SUM(I47:M47) -> 694.07398 | L67: =SUM(N47:R47) -> 521.77361 | M67: =SUM(S47:W47) -> 800.75856 | N67: =SUM(X47:AB47) -> 232.10385 | O67: =SUM(C67:N67) -> 5828.8948
B68: sweets/junk food | C68: =SUM(I7:M7)/72.7 -> 25.392022 | D68: =SUM(N7:R7)/72 -> 59.819444 | E68: =SUM(S7:W7) -> 73.05 | F68: =SUM(X7:AB7) -> 3 | G68: =SUM(I27:M27) -> 7 | H68: =SUM(N27:R27) -> 37.27 | I68: =SUM(S27:W27) -> 128.7 | J68: =SUM(X27:AB27) -> 6 | K68: =SUM(I48:M48) -> 0 | L68: =SUM(N48:R48) -> 14.000798 | M68: =SUM(S48:W48) -> 0 | N68: =SUM(X48:AB48) -> 0 | O68: =SUM(C68:N68) -> 354.23226
B69: ordered food/restaurant | C69: =SUM(I8:M8)/72.7 -> 109.83494 | D69: =SUM(N8:R8)/72 -> 155.43056 | E69: =SUM(S8:W8) -> 26.95 | F69: =SUM(X8:AB8) -> 22 | G69: =SUM(I28:M28) -> 60.5 | H69: =SUM(N28:R28) -> 90.4 | I69: =SUM(S28:W28) -> 0 | J69: =SUM(X28:AB28) -> 82.261905 | K69: =SUM(I49:M49) -> 393.37878 | L69: =SUM(N49:R49) -> 171.91671 | M69: =SUM(S49:W49) -> 261.36619 | N69: =SUM(X49:AB49) -> 37.525723 | O69: =SUM(C69:N69) -> 1411.5648
B70: electronics | C70: =SUM(I9:M9)/72.7 -> 0 | D70: =SUM(N9:R9)/72 -> 50.694444 | E70: =SUM(S9:W9) -> 5097 | F70: =SUM(X9:AB9) -> 300 | G70: =SUM(I29:M29) -> 145 | H70: =SUM(N29:R29) -> 83 | I70: =SUM(S29:W29) -> 0 | J70: =SUM(X29:AB29) -> 89.583333 | K70: =SUM(I50:M50) -> 1823.975 | L70: =SUM(N50:R50) -> 0 | M70: =SUM(S50:W50) -> 326.07319 | N70: =SUM(X50:AB50) -> 0 | O70: =SUM(C70:N70) -> 7915.326
B71: clothes | C71: =SUM(I10:M10)/72.7 -> 0 | D71: =SUM(N10:R10)/72 -> 0 | E71: =SUM(S10:W10) -> 89.98 | F71: =SUM(X10:AB10) -> 0 | G71: =SUM(I30:M30) -> 0 | H71: =SUM(N30:R30) -> 48.57 | I71: =SUM(S30:W30) -> 0 | J71: =SUM(X30:AB30) -> 41.607143 | K71: =SUM(I51:M51) -> 401.09707 | L71: =SUM(N51:R51) -> 164.52941 | M71: =SUM(S51:W51) -> 508.42298 | N71: =SUM(X51:AB51) -> 0 | O71: =SUM(C71:N71) -> 1254.2066
B72: gifts | C72: =SUM(I11:M11)/72.7 -> 0 | D72: =SUM(N11:R11)/72 -> 288.18056 | E72: =SUM(S11:W11) -> 117 | F72: =SUM(X11:AB11) -> 95 | G72: =SUM(I31:M31) -> 0 | H72: =SUM(N31:R31) -> 65 | I72: =SUM(S31:W31) -> 0 | J72: =SUM(X31:AB31) -> 34 | K72: =SUM(I52:M52) -> 0 | L72: =SUM(N52:R52) -> 0 | M72: =SUM(S52:W52) -> 0 | N72: =SUM(X52:AB52) -> 315.94512 | O72: =SUM(C72:N72) -> 915.12568
B73: transport | C73: =SUM(I12:M12)/72.7 -> 47.455296 | D73: =SUM(N12:R12)/72 -> 165.11111 | E73: =SUM(S12:W12) -> 26 | F73: =SUM(X12:AB12) -> 144 | G73: =SUM(I32:M32) -> 70 | H73: =SUM(N32:R32) -> 88 | I73: =SUM(S32:W32) -> 34 | J73: =SUM(X32:AB32) -> 626.59524 | K73: =SUM(I53:M53) -> 328.56783 | L73: =SUM(N53:R53) -> 114.12285 | M73: =SUM(S53:W53) -> 114.72044 | N73: =SUM(X53:AB53) -> 1949.2701 | O73: =SUM(C73:N73) -> 3707.8428
B74: others (crypto, etc.) | C74: =SUM(I13:M13)/72.7 -> 867.53521 | D74: =SUM(N13:R13)/72 -> 13.125 | E74: =SUM(S13:W13) -> 200 | F74: =SUM(X13:AB13) -> 20 | G74: =SUM(I33:M33) -> 17 | H74: =SUM(N33:R33) -> 150 | I74: =SUM(S33:W33) -> 30 | J74: =SUM(X33:AB33) -> 0 | K74: =SUM(I54:M54) -> 103.98326 | L74: =SUM(N54:R54) -> 148.2217 | M74: =SUM(S54:W54) -> 29.497099 | N74: =SUM(X54:AB54) -> 230.18641 | O74: =SUM(C74:N74) -> 1809.5487
B75: doctor, dentist, barber | C75: =SUM(I14:M14)/72.7 -> 68.775791 | D75: =SUM(N14:R14)/72 -> 421.66667 | I75: =SUM(S34:W34) -> 22 | J75: =SUM(X34:AB34) -> 167.61905 | K75: =SUM(I55:M55) -> 457.06285 | L75: =SUM(N55:R55) -> 863.29041 | M75: =SUM(S55:W55) -> 910.92421 | N75: =SUM(X55:AB55) -> 63.740229 | O75: =SUM(C75:N75) -> 2975.0792
B76: savings | C76: =SUM(I15:M15)/72.7 -> 3053.6451 | D76: =SUM(N15:R15)/72 -> 4751.4028 | E76: =SUM(S15:W15) -> 3510 | F76: =SUM(X15:AB15) -> 3910 | G76: =SUM(I35:M35) -> 4020 | H76: =SUM(N35:R35) -> 3652 | I76: =SUM(S35:W35) -> 3510 | J76: =SUM(X35:AB35) -> 8765 | K76: =SUM(I56:M56) -> 3899 | L76: =SUM(N56:R56) -> 3571 | M76: =SUM(S56:W56) -> 7980.7437 | N76: =SUM(X56:AB56) -> 8024.1732 | O76: =SUM(C76:N76) -> 58646.965
B77: OUT | C77: =SUM(C66:C75)+$C20+$C21 -> 2338.6934 | D77: =SUM(D66:D75)+$C20+$C21 -> 3126.4549 | E77: =SUM(E66:E75)+$C20+$C21 -> 7430.94 | F77: =SUM(F66:F75)+$C20+$C21 -> 1653.11 | G77: =SUM(G66:G75)+$C20+$C21 -> 1612.01 | H77: =SUM(H66:H75)+$C20+$C21 -> 1956.64 | I77: =SUM(I66:I75)+$C20+$C21 -> 1461.14 | J77: =SUM(J66:J75)+$C20+$C21 -> 6209.9576 | K77: =SUM(K66:K75)+$C20 -> 4231.6035 | L77: =SUM(L66:L75)+$C20 -> 2974.2748 | M77: =SUM(M66:M75)+$C20 -> 4040.1981 | N77: =SUM(N66:N75)+$C20 -> 5421.9569
B78: IN | C78: =C76 -> 3053.6451 | D78: =D76 -> 4751.4028 | E78: =E76 -> 3510 | F78: =F76 -> 3910 | G78: =G76 -> 4020 | H78: =H76 -> 3652 | I78: =I76 -> 3510 | J78: =J76 -> 8765 | ... N78: =N76 -> 8024.1732
B79: Total | C79: =(C78 - C77) -> 714.95172 | D79: =(D78 - D77) -> 1624.9479 | E79: =(E78 - E77) -> -3920.94 | F79: =(F78 - F77) -> 2256.89 | G79: =(G78 - G77) -> 2407.99 | H79: =(H78 - H77) -> 1695.36 | I79: =(I78 - I77) -> 2048.86 | J79: =(J78 - J77) -> 2555.0424 | ... N79: =(N78 - N77) -> 2602.2163
B80: Total out | C80: =SUM(C77:N77) -> 42456.979
B81: Total in | C81: =SUM(C78:N78) -> 58646.965
B82: Sum | C82: =(C81-C80) -> 16189.986

Sheet 2021
A1: I spent this much money on this kinda shit
H3: Hónap | I3: JAN | N3: FEB | S3: MÁR | X3: ÁPR
B4: Code | C4: Description | H4: Hét | I4: 1 | J4: 2 | K4: 3 | L4: 4 | M4: 5 | N4: 1 | O4: 2 | P4: 3 | Q4: 4 | R4: 5 | S4: 1 | T4: 2 | U4: 3 | V4: 4 | W4: 5 | X4: 1 | Y4: 2 | Z4: 3 | AA4: 4 | AB4: 5
B5: A | C5: rent+utilities | I5: 320 | J5: 53 | K5: 100 | L5: 30 | N5: 320 | O5: 50 | P5: 20 | Q5: 39 | S5: 323 | T5: 100 | U5: 92 | X5: 328 | Y5: 50 | Z5: 45
B6: B | C6: basic food and stuff | I6: 157 | J6: 8 | K6: 100 | L6: 30 | M6: 3 | N6: 30 | O6: 26 | P6: 60 | Q6: 86 | R6: 83 | S6: 44 | T6: 199 | U6: 45 | V6: 37 | W6: 57 | X6: 83 | Y6: 71 | Z6: 44 | AA6: 77 | AB6: 103
B7: C | C7: sweets/junk food | I7: 10 | U7: 0 | Z7: 13 | AB7: 10
B8: D | C8: ordered food | I8: 70 | J8: 20 | K8: 31 | N8: 33 | P8: 66 | R8: 63 | S8: 33 | T8: 25
B9: E | C9: electronics | I9: 160 | J9: 2322 | N9: 50 | O9: 50 | S9: 560 | Z9: 50
B10: F | C10: clothes | I10: 60 | N10: 45 | R10: 56 | U10: 0 | AB10: 167
B11: G | C11: gifts | R11: 86
B12: H | C12: transport | X12: 92 | AA12: 8
B13: I | C13: others (crypto, entertainment, skincare, etc.)
B14: J | C14: dentist, doctor, barber
B15: K | C15: savings | I15: 1500 | J15: 320 | N15: 100 | P15: 1500 | Q15: 800 | S15: 27 | T15: 100 | U15: 800 | V15: 1500 | X15: 50 | Y15: 1500 | Z15: 800
B16: X | C16: out | S16: AOC Monitor | X16: husvet
B17: Y | C17: in | R17: Ebay adidas hoodie | AB17: NED88 mez
B18: Z | C18: total
B19: Constants every month:
B20: Netflix | C20: 10
B21: YOXO | C21: 16
I23: MÁJ | N23: JÚN | S23: JÚL | X23: AUG
I24: 1 | J24: 2 | K24: 3 | L24: 4 | M24: 5 | N24: 1 | O24: 2 | P24: 3 | Q24: 4 | R24: 5 | S24: 1 | T24: 2 | U24: 3 | V24: 4 | W24: 5 | X24: 1 | Y24: 2 | Z24: 3 | AA24: 4 | AB24: 5
H25: rent+utilities | I25: 328 | J25: 69 | N25: 329 | O25: 86 | R25: 88 | S25: 340 | T25: 87 | X25: 340 | Y25: 87 | AA25: =0*0.014 -> 0 | AB25: =11000*0.014 -> 154
H26: basic food and stuff | I26: 92 | J26: 74 | K26: 62 | L26: 97 | M26: 107 | N26: 66 | O26: =55+10+10+5+15.8 -> 95.8 | P26: =3+62 -> 65 | Q26: 48 | S26: =3+8.4 -> 11.4 | T26: =90+27 -> 117 | V26: =86+10+20 -> 116 | W26: =92+10 -> 102 | X26: =37+18+36 -> 91 | Y26: =62+25+10+18.38+35 -> 150.38 | Z26: =46 -> 46 | AA26: =0*0.014 -> 0 | AB26: =(2685+750+3570)*0.014 -> 98.07
H27: sweets/junk food | K27: 10 | L27: 5 | M27: 16.5 | T27: 8 | Z27: 15 | AA27: =0*0.014 -> 0 | AB27: =(2250+258)*0.014 -> 35.112
H28: ordered food | O28: 31 | P28: 34 | Q28: 42 | T28: 34 | V28: 22 | Y28: =6+29 -> 35 | Z28: 35 | AA28: =0*0.014 -> 0 | AB28: =0*0.014 -> 0
H29: electronics | L29: 45 | V29: =2600+160 -> 2760 | AA29: =0*0.014 -> 0 | AB29: =0/0.014 -> 0
H30: clothes | M30: =34+40 -> 74 | O30: 25 | Q30: =24+52 -> 76 | X30: 25.5 | Z30: =70 -> 70 | AA30: =0*0.014 -> 0 | AB30: =0/0.014 -> 0
H31: gifts | M31: 40 | AA31: =0*0.014 -> 0 | AB31: =0/0.014 -> 0
H32: transport | J32: 30 | N32: 8 | W32: 80 | Y32: 22 | Z32: =30+25 -> 55 | AA32: 0 | AB32: 0
H33: others (crypto, etc.) | J33: 50 | O33: =50+30 -> 80 | P33: 305 | U33: 48 | V33: =110+86+71 -> 267 | AA33: 0 | AB33: 0
H34: services(doctor, dentist, barber, massage) | Y34: =220+200 -> 420 | AA34: =0*0.014 -> 0 | AB34: 30
H35: savings | J35: 1000 | K35: 1500 | N35: 1500 | O35: 1000 | S35: 1500 | T35: 800 | Y35: 300 | Z35: 1500 | AA35: 800 | AB35: 950
H36: X | J36: ETDK | V36: Iphone 12 mini + chargers | AB36: BP szallas
H37: Y | AB37: roaming
H38: Z
H42: 72 | I42: FORINT
H43: BUDAPEST | I43: SZEP | N43: OKT | S43: NOV | X43: DEC
I44: 1 | J44: 2 | K44: 3 | L44: 4 | M44: 5 | N44: 1 | O44: 2 | P44: 3 | Q44: 4 | R44: 5 | S44: 1 | T44: 2 | U44: 3 | V44: 4 | W44: 5 | X44: 1 | Y44: 2 | Z44: 3 | AA44: 4 | AB44: 5
H45: rent+utilities | I45: 55000 | N45: =45000+10000 -> 55000 | S45: 55000 | X45: 55000
H46: basic food and stuff | I46: =3890-1190 -> 2700 | J46: =3860+219+800+4500+1485 -> 10864 | K46: =710+280+3069+1005 -> 5064 | L46: =1231+719+2274 -> 4224 | M46: =449+4463 -> 4912 | N46: =4032+2805+714+1091 -> 8642 | O46: =5500 -> 5500 | P46: =654+1559+973+911 -> 4097 | Q46: =2680+350 -> 3030 | R46: =2350+600+479+1627+4261 -> 9317 | S46: =1059+2003+2148 -> 5210 | T46: =2979+2120+1000+6799+589-2496-1900 -> 9091 | U46: =1831-600+1620+7344 -> 10195 | V46: =1200+280+280+2253+300+280 -> 4593 | W46: 280 | X46: =280+600+3700+300+365 -> 5245 | Z46: =13000+600 -> 13600 | AA46: =153*73 -> 11169
H47: sweets/junk food | I47: 1200 | K47: =495 -> 495 | V47: 315
H48: ordered food/restaurant | J48: =4184 -> 4184 | K48: =1380 -> 1380 | L48: =500+500 -> 1000 | U48: =740+870 -> 1610 | V48: 4200 | X48: =1450+3000 -> 4450
H49: electronics | J49: =650+650 -> 1300 | V49: 190000 | Y49: 15000
H50: clothes | I50: 7450 | O50: =6995 -> 6995 | T50: =2990 -> 2990
H51: gifts | J51: 4500
H52: transport & travel | J52: =2100 -> 2100 | N52: =3450 -> 3450 | R52: =4600+11000 -> 15600 | S52: =9000 -> 9000 | X52: 3450 | Y52: =1244*73 -> 90812
H53: others (entertainment, crypto, etc.) | I53: 10000 | K53: =1990 -> 1990 | L53: 1000 | Q53: =47*70 -> 3290 | T53: =2925-975-975 -> 975 | W53: =(531.82*73.43) + (485.24*73.43) -> 74682.716
H54: services(football, doctor, dentist, barber, massage) | I54: 3000 | N54: 3600 | Q54: 1000 | R54: 1000 | T54: =3000+1000 -> 4000 | U54: =1000 -> 1000 | V54: 1000 | W54: 1000 | X54: =1000 -> 1000 | Y54: 1000 | Z54: 1000 | AA54: 1000
H55: savings | J55: =3000*70 -> 210000 | K55: 57865 | N55: 222204 | S55: 36365 | T55: =222000 -> 222000 | X55: =518000 -> 518000
H56: X | K56: pingpong | Y56: alza - tok,folia
H57: Y | Y57: BELGIA
H58: Z
B62: 2021
B64: Type | C64: JAN | D64: FEB | E64: MAR | F64: APR | G64: MAJ | H64: JUN | I64: JUL | J64: AUG | K64: SZE | L64: OKT | M64: NOV | N64: DEC | O64: Total Cat.
B65: rent+utilities | C65: =SUM(I5:M5) -> 503 | D65: =SUM(N5:R5) -> 429 | E65: =SUM(S5:W5) -> 515 | F65: =SUM(X5:AB5) -> 423 | G65: =SUM(I25:M25) -> 397 | H65: =SUM(N25:R25) -> 503 | I65: =SUM(S25:W25) -> 427 | J65: =SUM(X25:AB25) -> 581 | K65: =SUM(I45:M45)/H42 -> 763.88889 | L65: =SUM(N45:R45)/$H$42 -> 763.88889 | M65: =SUM(S45:W45)/74 -> 743.24324 | N65: =SUM(X45:AB45)/74 -> 743.24324 | O65: =SUM(C65:N65) -> 6792.2643
B66: basic food and stuff | C66: =SUM(I6:M6) -> 298 | D66: =SUM(N6:R6) -> 285 | E66: =SUM(S6:W6) -> 382 | F66: =SUM(X6:AB6) -> 378 | G66: =SUM(I26:M26) -> 432 | H66: =SUM(N26:R26) -> 274.8 | I66: =SUM(S26:W26) -> 346.4 | J66: =SUM(X26:AB26) -> 385.45 | K66: =SUM(I46:M46)/70 -> 396.62857 | L66: =SUM(N46:R46)/$H$42 -> 424.80556 | M66: =SUM(S46:W46)/74 -> 396.87838 | N66: =SUM(X46:AB46)/74 -> 405.59459 | O66: =SUM(C66:N66) -> 4405.5571
B67: sweets/junk food | C67: =SUM(I7:M7) -> 10 | D67: =SUM(N7:R7) -> 0 | E67: =SUM(S7:W7) -> 0 | F67: =SUM(X7:AB7) -> 23 | G67: =SUM(I27:M27) -> 31.5 | H67: =SUM(N27:R27) -> 0 | I67: =SUM(S27:W27) -> 8 | J67: =SUM(X27:AB27) -> 50.112 | K67: =SUM(I47:M47)/70 -> 24.214286 | L67: =SUM(N47:R47)/$H$42 -> 0 | M67: =SUM(S47:W47)/74 -> 4.2567568 | N67: =SUM(X47:AB47)/74 -> 0 | O67: =SUM(C67:N67) -> 151.08304
B68: ordered food/restaurant | C68: =SUM(I8:M8) -> 121 | D68: =SUM(N8:R8) -> 162 | E68: =SUM(S8:W8) -> 58 | F68: =SUM(X8:AB8) -> 0 | G68: =SUM(I28:M28) -> 0 | H68: =SUM(N28:R28) -> 107 | I68: =SUM(S28:W28) -> 56 | J68: =SUM(X28:AB28) -> 70 | K68: =SUM(I48:M48)/70 -> 93.771429 | L68: =SUM(N48:R48)/$H$42 -> 0 | M68: =SUM(S48:W48)/74 -> 78.513514 | N68: =SUM(X48:AB48)/74 -> 60.135135 | O68: =SUM(C68:N68) -> 806.42008
B69: electronics | C69: =SUM(I9:M9) -> 2482 | D69: =SUM(N9:R9) -> 100 | E69: =SUM(S9:W9) -> 560 | F69: =SUM(X9:AB9) -> 50 | G69: =SUM(I29:M29) -> 45 | H69: =SUM(N29:R29) -> 0 | I69: =SUM(S29:W29) -> 2760 | J69: =SUM(X29:AB29) -> 0 | K69: =SUM(I49:M49)/70 -> 18.571429 | L69: =SUM(N49:R49)/$H$42 -> 0 | M69: =SUM(S49:W49)/74 -> 2567.5676 | N69: =SUM(X49:AB49)/74 -> 202.7027 | O69: =SUM(C69:N69) -> 8785.8417
B70: clothes | C70: =SUM(I10:M10) -> 60 | D70: =SUM(N10:R10) -> 101 | E70: =SUM(S10:W10) -> 0 | F70: =SUM(X10:AB10) -> 167 | G70: =SUM(I30:M30) -> 74 | H70: =SUM(N30:R30) -> 101 | I70: =SUM(S30:W30) -> 0 | J70: =SUM(X30:AB30) -> 95.5 | K70: =SUM(I50:M50)/70 -> 106.42857 | L70: =SUM(N50:R50)/$H$42 -> 97.152778 | M70: =SUM(S50:W50)/74 -> 40.405405 | N70: =SUM(X50:AB50)/74 -> 0 | O70: =SUM(C70:N70) -> 842.48675
B71: gifts | C71: =SUM(I11:M11) -> 0 | D71: =SUM(N11:R11) -> 86 | E71: =SUM(S11:W11) -> 0 | F71: =SUM(X11:AB11) -> 0 | G71: =SUM(I31:M31) -> 40 | H71: =SUM(N31:R31) -> 0 | I71: =SUM(S31:W31) -> 0 | J71: =SUM(X31:AB31) -> 0 | K71: =SUM(I51:M51)/70 -> 64.285714 | L71: =SUM(N51:R51)/$H$42 -> 0 | M71: =SUM(S51:W51)/74 -> 0 | N71: =SUM(X51:AB51)/74 -> 0 | O71: =SUM(C71:N71) -> 190.28571
B72: transport | C72: =SUM(I12:M12) -> 0 | D72: =SUM(N12:R12) -> 0 | E72: =SUM(S12:W12) -> 0 | F72: =SUM(X12:AB12) -> 100 | G72: =SUM(I32:M32) -> 30 | H72: =SUM(N32:R32) -> 8 | I72: =SUM(S32:W32) -> 80 | J72: =SUM(X32:AB32) -> 77 | K72: =SUM(I52:M52)/70 -> 30 | L72: =SUM(N52:R52)/$H$42 -> 264.58333 | M72: =SUM(S52:W52)/74 -> 121.62162 | N72: =SUM(X52:AB52)/74 -> 1273.8108 | O72: =SUM(C72:N72) -> 1985.0158
B73: others (crypto, etc.) | C73: =SUM(I13:M13) -> 0 | D73: =SUM(N13:R13) -> 0 | E73: =SUM(S13:W13) -> 0 | F73: =SUM(X13:AB13) -> 0 | G73: =SUM(I33:M33) -> 50 | H73: =SUM(N33:R33) -> 385 | I73: =SUM(S33:W33) -> 315 | J73: =SUM(X33:AB33) -> 0 | K73: =SUM(I53:M53)/70 -> 185.57143 | L73: =SUM(N53:R53)/$H$42 -> 45.694444 | M73: =SUM(S53:W53)/74 -> 1022.4016 | N73: =SUM(X53:AB53)/74 -> 0 | O73: =SUM(C73:N73) -> 2003.6674
B74: doctor, dentist, barber | I74: =SUM(S34:W34) -> 0 | J74: =SUM(X34:AB34) -> 450 | K74: =SUM(I54:M54)/70 -> 42.857143 | L74: =SUM(N54:R54)/$H$42 -> 77.777778 | M74: =SUM(S54:W54)/74 -> 94.594595 | N74: =SUM(X54:AB54)/74 -> 54.054054 | O74: =SUM(C74:N74) -> 719.28357
B75: savings | C75: =SUM(I15:M15) -> 1820 | D75: =SUM(N15:R15) -> 2400 | E75: =SUM(S15:W15) -> 2427 | F75: =SUM(X15:AB15) -> 2350 | G75: =SUM(I35:M35) -> 2500 | H75: =SUM(N35:R35) -> 2500 | I75: =SUM(S35:W35) -> 2300 | J75: =SUM(X35:AB35) -> 3550 | K75: =SUM(I55:M55)/70 -> 3826.6429 | L75: =SUM(N55:R55)/$H$42 -> 3086.1667 | M75: =SUM(S55:W55)/74 -> 3491.4189 | N75: =SUM(X55:AB55)/73 -> 7095.8904 | O75: =SUM(C75:N75) -> 37347.119
B76: OUT | C76: =SUM(C65:C73)+$C20+$C21 -> 3500 | D76: =SUM(D65:D73)+$C20+$C21 -> 1189 | E76: =SUM(E65:E73)+$C20+$C21 -> 1541 | F76: =SUM(F65:F73)+$C20+$C21 -> 1167 | G76: =SUM(G65:G73)+$C20+$C21 -> 1125.5 | H76: =SUM(H65:H73)+$C20+$C21 -> 1404.8 | I76: =SUM(I65:I73)+$C20+$C21 -> 4018.4 | J76: =SUM(J65:J71)+$C20+$C21 -> 1208.062 | K76: =SUM(K65:K74)+$C20 -> 1736.2175 | L76: =SUM(L65:L71)+$C20 -> 1295.8472 | M76: =SUM(M65:M74)+$C20 -> 5079.4826 | N76: =SUM(N65:N74)+$C20 -> 2749.5405
B77: IN | C77: =C75 -> 1820 | D77: =D75 -> 2400 | E77: =E75 -> 2427 | F77: =F75 -> 2350 | G77: =G75 -> 2500 | H77: =H75 -> 2500 | I77: =I75 -> 2300 | J77: =J75 -> 3550 | ... N77: =N75 -> 7095.8904
B78: Total | C78: =(C77 - C76) -> -1680 | D78: =(D77 - D76) -> 1211 | E78: =(E77 - E76) -> 886 | F78: =(F77 - F76) -> 1183 | G78: =(G77 - G76) -> 1374.5 | H78: =(H77 - H76) -> 1095.2 | I78: =(I77 - I76) -> -1718.4 | J78: =(J77 - J76) -> 2341.938 | ... N78: =(N77 - N76) -> 4346.3499
B79: Total out | C79: =SUM(C76:N76) -> 26014.85
B80: Total in | C80: =SUM(C77:N77) -> 37347.119
B81: Sum | C81: =(C80-C79) -> 11332.269

Sheet Assets
A2: Name | B2: Type | C2: Value | D2: Currency | H2: Currency | I2: EUR Rate
A3: Revolut EUR | B3: Savings | C3: 713.33 | D3: EUR | H3: RON | I3: 0.2
A4: Revolut RON | B4: Spending | C4: 7263.42 | D4: RON | H4: HUF | I4: 0.0025
A5: Revolut HUF | B5: Spending | C5: 6380.56 | D5: HUF | H5: USD | I5: 1
A6: OTP RON | B6: Void | C6: 7733.86 | D6: RON
A7: ERSTE HUF | B7: Salary | C7: 521942 | D7: HUF
A8: Binance | B8: Crypto | C8: 14.2 | D8: USD
A9: Trade212 | B9: Invest | C9: 102.78 | D9: RON
A10: Total | B10: - | C10: =SUMIF($D$3:$D$9,D10,$C$3:$C$9) -> 713.33 | D10: EUR
C11: =SUMIF($D$3:$D$9,D11,$C$3:$C$9) -> 528322.56 | D11: HUF
C12: =SUMIF($D$3:$D$9,D12,$C$3:$C$9) -> 7836.64 | D12: RON
C13: =(C10 + C11*I4 + C12*I3) -> 3601.4644 | D13: ALL

Sheet Investments
B2: Investments
B3: Funds & Stocks Portfolio
B4: Type | C4: Exchange | D4: Region | E4: Currency | G4: Name | H4: Ticker | I4: # | J4: ACC | K4: Invested (USD) | L4: Invested (EUR) | M4: Value (EUR) | N4: Value (USD) | O4: Gain (%) | P4: % | Q4: Price (EUR) | R4: Price (USD)
B5: STOCK | C5: NASDAQ | D5: USA | E5: =IFERROR(__xludf.DUMMYFUNCTION("IF(ISBLANK(H5), ""-"", GOOGLEFINANCE(IF(ISBLANK(C5), H5, C5&"":""&H5), ""currency""))"),"USD") -> USD | G5: Apple | H5: AAPL | I5: 4.1868055 | J5: - | K5: =(4.058092893* 179.96+0.128712567*186.24) -> 754.26583 | L5: =K5*E18 -> 655.01199 | M5: =I5*Q5 -> 1212.306 | N5: =I5*R5 -> 1396.0065 | O5: =if(K5=0,0,(N5-K5)/K5) -> 0.85081505 | P5: =M5/($I17) -> 0.19314432 | Q5: =IFERROR(__xludf.DUMMYFUNCTION("if(E5 = ""USD"",R5*GoogleFinance(""CURRENCY:USDEUR""),GOOGLEFINANCE(IF(ISBLANK(C5), H5, C5&"":""&H5), ""Price""))"),289.5539463) -> 289.55395 | R5: =IFERROR(__xludf.DUMMYFUNCTION("if(E5 = ""USD"",GOOGLEFINANCE(IF(ISBLANK(C5), H5, C5&"":""&H5), ""Price""),Q5*GoogleFinance(""CURRENCY:EURUSD""))"),333.43) -> 333.43
B6: STOCK | C6: NASDAQ | D6: USA | E6: =IFERROR(__xludf.DUMMYFUNCTION("IF(ISBLANK(H6), ""-"", GOOGLEFINANCE(IF(ISBLANK(C6), H6, C6&"":""&H6), ""currency""))"),"USD") -> USD | G6: NVidia | H6: NVDA | I6: 0.9780213 | J6: - | K6: =(0.099779546*660.46 + 0.878241758*682.5) -> 665.3004 | L6: =K6*E18 -> 577.75352 | M6: =I6*Q6 -> 165.65205 | N6: =I6*R6 -> 190.75328 | O6: =if(K6=0,0,(N6-K6)/K6) -> -0.71328249 | P6: =M6/I17 -> 0.026391646 | Q6: =IFERROR(__xludf.DUMMYFUNCTION("if(E6 = ""USD"",R6*GoogleFinance(""CURRENCY:USDEUR""),GOOGLEFINANCE(IF(ISBLANK(C6), H6, C6&"":""&H6), ""Price""))"),169.3746864) -> 169.37469 | R6: =IFERROR(__xludf.DUMMYFUNCTION("if(E6 = ""USD"",GOOGLEFINANCE(IF(ISBLANK(C6), H6, C6&"":""&H6), ""Price""),Q6*GoogleFinance(""CURRENCY:EURUSD""))"),195.04) -> 195.04
B7: STOCK | C7: NYSE | D7: EU | E7: =IFERROR(__xludf.DUMMYFUNCTION("IF(ISBLANK(H7), ""-"", GOOGLEFINANCE(IF(ISBLANK(C7), H7, C7&"":""&H7), ""currency""))"),"USD") -> USD | G7: Novo Nordisk | H7: NVO | I7: 3.41659 | J7: - | K7: =(1.716642323 * 116.39 + 1.623371113*117.82 + 0.076576576 * 118.41) -> 400.13302 | L7: =K7*E18 -> 347.47951 | M7: =I7*Q7 -> 153.12692 | N7: =I7*R7 -> 176.33021 | O7: =if(K7=0,0,(N7-K7)/K7) -> -0.55932102 | P7: =M7/I17 -> 0.024396145 | Q7: =IFERROR(__xludf.DUMMYFUNCTION("if(E7 = ""USD"",R7*GoogleFinance(""CURRENCY:USDEUR""),GOOGLEFINANCE(IF(ISBLANK(C7), H7, C7&"":""&H7), ""Price""))"),44.8186401) -> 44.81864 | R7: =IFERROR(__xludf.DUMMYFUNCTION("if(E7 = ""USD"",GOOGLEFINANCE(IF(ISBLANK(C7), H7, C7&"":""&H7), ""Price""),Q7*GoogleFinance(""CURRENCY:EURUSD""))"),51.61) -> 51.61
B8: STOCK | C8: NYSE | D8: EU | E8: =IFERROR(__xludf.DUMMYFUNCTION("IF(ISBLANK(H8), ""-"", GOOGLEFINANCE(IF(ISBLANK(C8), H8, C8&"":""&H8), ""currency""))"),"USD") -> USD | G8: Spotify | H8: SPOT | I8: =0.053302062+0.145933266 -> 0.19923533 | J8: - | K8: =(0.053302062*187.61)+(0.145933266*231.34) -> 43.760202 | L8: =9.29+33.86 -> 43.15 | M8: =I8*Q8 -> 90.420911 | N8: =I8*R8 -> 104.12237 | O8: =if(K8=0,0,(N8-K8)/K8) -> 1.3793852 | P8: =M8/I17 -> 0.014405839 | Q8: =IFERROR(__xludf.DUMMYFUNCTION("if(E8 = ""USD"",R8*GoogleFinance(""CURRENCY:USDEUR""),GOOGLEFINANCE(IF(ISBLANK(C8), H8, C8&"":""&H8), ""Price""))"),453.8397501) -> 453.83975 | R8: =IFERROR(__xludf.DUMMYFUNCTION("if(E8 = ""USD"",GOOGLEFINANCE(IF(ISBLANK(C8), H8, C8&"":""&H8), ""Price""),Q8*GoogleFinance(""CURRENCY:EURUSD""))"),522.61) -> 522.61
B9: ETF | C9: BIT | D9: EU | E9: =IFERROR(__xludf.DUMMYFUNCTION("IF(ISBLANK(H9), ""-"", GOOGLEFINANCE(IF(ISBLANK(C9), H9, C9&"":""&H9), ""currency""))"),"EUR") -> EUR | G9: Vanguard FTSE All World | H9: VWCE | I9: =16+15+1+5+4 -> 41 | J9: 228.14 | K9: =L9*1.08 -> 4988.8332 | L9: =(3*111.9+12*112.02+1*112+15*112.54+112.55+5*112.54+4*116) -> 4619.29 | M9: =L9+J9 -> 4847.43 | N9: =IFERROR(__xludf.DUMMYFUNCTION("M9*GoogleFinance(""CURRENCY:EURUSD"")"),5581.8641193) -> 5581.8641 | O9: =if(K9=0,0,(N9-K9)/K9) -> 0.11887167 | P9: =M9/I17 -> 0.77229142 | Q9: =IFERROR(__xludf.DUMMYFUNCTION("if(E9 = ""USD"",R9*GoogleFinance(""CURRENCY:USDEUR""),GOOGLEFINANCE(IF(ISBLANK(C9), H9, C9&"":""&H9), ""Price""))"),164.24) -> 164.24 | R9: =IFERROR(__xludf.DUMMYFUNCTION("if(E9 = ""USD"",GOOGLEFINANCE(IF(ISBLANK(C9), H9, C9&"":""&H9), ""Price""),Q9*GoogleFinance(""CURRENCY:EURUSD""))"),189.12400240000002) -> 189.124
H10: CSPX | I10: 0 | K10: 0 | L10: =IFERROR(__xludf.DUMMYFUNCTION("K10*GoogleFinance(""CURRENCY:USDEUR"")"),0.0) -> 0 | M10: =I10*Q10 -> 0 | N10: =I10*R10 -> 0 | O10: =if(K10=0,0,(N10-K10)/K10) -> 0 | P10: =M10/I17 -> 0 | Q10: =IFERROR(__xludf.DUMMYFUNCTION("if(E10 = ""USD"",R10*GoogleFinance(""CURRENCY:USDEUR""),GOOGLEFINANCE(IF(ISBLANK(C10), H10, C10&"":""&H10), ""Price""))"),806.29) -> 806.29 | R10: =IFERROR(__xludf.DUMMYFUNCTION("if(E10 = ""USD"",GOOGLEFINANCE(IF(ISBLANK(C10), H10, C10&"":""&H10), ""Price""),Q10*GoogleFinance(""CURRENCY:EURUSD""))"),928.4509979) -> 928.451
H11: IWDA | I11: 0 | K11: 0 | L11: =IFERROR(__xludf.DUMMYFUNCTION("K11*GoogleFinance(""CURRENCY:USDEUR"")"),0.0) -> 0 | M11: =I11*Q11 -> 0 | N11: =I11*R11 -> 0 | O11: =if(K11=0,0,(N11-K11)/K11) -> 0 | P11: =M11/I17 -> 0 | Q11: =IFERROR(__xludf.DUMMYFUNCTION("if(E11 = ""USD"",R11*GoogleFinance(""CURRENCY:USDEUR""),GOOGLEFINANCE(IF(ISBLANK(C11), H11, C11&"":""&H11), ""Price""))"),144.08) -> 144.08 | R11: =IFERROR(__xludf.DUMMYFUNCTION("if(E11 = ""USD"",GOOGLEFINANCE(IF(ISBLANK(C11), H11, C11&"":""&H11), ""Price""),Q11*GoogleFinance(""CURRENCY:EURUSD""))"),165.9095608) -> 165.90956
H12: VUAA | I12: 0 | K12: 0 | L12: =IFERROR(__xludf.DUMMYFUNCTION("K12*GoogleFinance(""CURRENCY:USDEUR"")"),0.0) -> 0 | M12: =I12*Q12 -> 0 | N12: =I12*R12 -> 0 | O12: =if(K12=0,0,(N12-K12)/K12) -> 0 | P12: =M12/I17 -> 0 | Q12: =IFERROR(__xludf.DUMMYFUNCTION("if(E12 = ""USD"",R12*GoogleFinance(""CURRENCY:USDEUR""),GOOGLEFINANCE(IF(ISBLANK(C12), H12, C12&"":""&H12), ""Price""))"),144.64) -> 144.64 | R12: =IFERROR(__xludf.DUMMYFUNCTION("if(E12 = ""USD"",GOOGLEFINANCE(IF(ISBLANK(C12), H12, C12&"":""&H12), ""Price""),Q12*GoogleFinance(""CURRENCY:EURUSD""))"),166.55440639999998) -> 166.55441
H13: META | I13: 0 | K13: 0 | L13: =IFERROR(__xludf.DUMMYFUNCTION("K13*GoogleFinance(""CURRENCY:USDEUR"")"),0.0) -> 0 | M13: =I13*R13 -> 0 | N13: =I13*R13 -> 0 | O13: =if(K13=0,0,(N13-K13)/K13) -> 0 | P13: =M13/I17 -> 0 | Q13: =IFERROR(__xludf.DUMMYFUNCTION("if(E13 = ""USD"",R13*GoogleFinance(""CURRENCY:USDEUR""),GOOGLEFINANCE(IF(ISBLANK(C13), H13, C13&"":""&H13), ""Price""))"),539.03) -> 539.03 | R13: =IFERROR(__xludf.DUMMYFUNCTION("if(E13 = ""USD"",GOOGLEFINANCE(IF(ISBLANK(C13), H13, C13&"":""&H13), ""Price""),Q13*GoogleFinance(""CURRENCY:EURUSD""))"),620.6984353) -> 620.69844
E14: EUR | G14: CASH | H14: - | I14: 1 | K14: =L14*F17 -> 39.15134 | L14: 34 | M14: 34 | N14: =IFERROR(__xludf.DUMMYFUNCTION("L14*GoogleFinance(""CURRENCY:EURUSD"")"),39.151340000000005) -> 39.15134 | O14: 0 | P14: =M14/$I17 -> 0.0054168721 | Q14: =M14 -> 34 | R14: =IFERROR(__xludf.DUMMYFUNCTION("Q14*GoogleFinance(""CURRENCY:EURUSD"")"),39.151340000000005) -> 39.15134
I15: Summary
E16: EUR | F16: USD | H16: Total | I16: Gains 💪🏻💸 | O16: Growth 🕑
E17: 1 | F17: =IFERROR(__xludf.DUMMYFUNCTION("E17*GoogleFinance(""CURRENCY:EURUSD"")"),1.15151) -> 1.15151 | H17: Invested | I17: =SUM(L5:L14) -> 6276.685 | O17: 1
E18: =IFERROR(__xludf.DUMMYFUNCTION("F18*GoogleFinance(""CURRENCY:USDEUR"")"),0.86841) -> 0.86841 | F18: 1 | H18: Value | I18: =SUM(M5:M14) -> 6502.9359 | O18: =I18/I17 -> 1.0360462
H19: Gained | I19: =I18-I17 -> 226.25091 | O19: =O18-O17 -> 0.036046242
U22: ACCUMULATED GAINS | AH22: RECURRING INVESTMENT | AI22: EXP. GROWTH /MONTH (%)
T23: TOTAL | U23: JAN | V23: FEB | W23: MAR | X23: APR | Y23: MAY | Z23: JUN | AA23: JUL | AB23: AUG | AC23: SEP | AD23: OCT | AE23: NOV | AF23: DEC | AH23: 800 | AI23: 2.5
T24: invested | U24: 739 | V24: =5905 -> 5905 | W24: =I17 -> 6276.685 | X24: =I17 -> 6276.685 | Y24: =8309-613 -> 7696 | Z24: 8309 | AA24: =7322+1000 -> 8322 | AB24: =8799+980 -> 9779 | AC24: =AB26+$AH23 -> 10823.475 | AD24: =AC26+$AH23 -> 11894.062 | AE24: =AD26+$AH23 -> 12991.413 | AF24: =AE26+$AH23 -> 14116.199
T25: reached | U25: 751.69 | V25: 6100 | W25: 6817 | X25: =I18 -> 6502.9359 | Y25: 8200 | Z25: 8309 | AA25: =1433+7761 -> 9194 | AB25: =9318+1565 -> 10883 | AC25: 0 | AD25: 0 | AE25: 0 | AF25: 0
T26: projected | U26: =U24+(U24*$AI23/100) -> 757.475 | V26: =V24+(V24*$AI23/100) -> 6052.625 | W26: =W24+(W24*$AI23/100) -> 6433.6021 | X26: =X24+(X24*$AI23/100) -> 6433.6021 | Y26: =Y24+(Y24*$AI23/100) -> 7888.4 | Z26: =Z24+(Z24*$AI23/100) -> 8516.725 | AA26: =AA24+(AA24*$AI23/100) -> 8530.05 | AB26: =AB24+(AB24*$AI23/100) -> 10023.475 | ... AF26: =AF24+(AF24*$AI23/100) -> 14469.104
T27: growth | U27: 0 | V27: =V25/V24 - 1 -> 0.033022862 | W27: =W25/W24 - 1 -> 0.086082857 | X27: =X25/X24 - 1 -> 0.036046242 | Y27: =Y25/Y24 - 1 -> 0.065488565 | Z27: =Z25/Z24 - 1 -> 0 | AA27: =AA25/AA24 - 1 -> 0.1047825 | AB27: =AB25/AB24 - 1 -> 0.11289498
U28: 24/01 | V28: 24/02 | W28: 24/03 | X28: 24/04 | Y28: 24/05 | Z28: 24/06 | AA28: 24/07 | AB28: 24/08 | AC28: 24/09 | AD28: 24/10 | AE28: 24/11 | AF28: 24/12
G32: V
